Workbook

Sheet 📋 Instructions
A1: BSS/OSS LM Studio Development Master Tracker
A2: Version 1.0 | Strategy: Zero-Flaw TDD with 12GB GPU
A4: HOW TO USE THIS WORKBOOK
A6: Sheet | B6: Purpose | C6: When to use
A7: 📋 Instructions | B7: This sheet — legend, column guide, workflow rules | C7: Read first, keep open
A8: 🔧 Environment Setup | B8: One-time machine setup tasks before writing any code | C8: Day 0
A9: 🗄️ DB Migrations | B9: All 15 goose migration sessions, one table per session | C9: Week 1-2
A10: 🔐 Crypto Module | B10: AES-GCM-256 PII encryption — zero-dependency module | C10: Week 3
A11: 📡 RADIUS AAA | B11: Worker pool, auth, dedup, FUP, observability | C11: Week 4-5
A12: 💳 Billing Module | B12: GST, wallet, dunning, GSTR-1, invoice PDF | C12: Week 6-7
A13: 🔔 Notifications | B13: WhatsApp/SMS/Email dispatcher, DND, delivery log | C13: Week 8
A14: ⚡ FUP + Asynq | B14: FUP scanner, CoA/PoD tasks, dead-letter monitor | C14: Week 9
A15: 🔑 API + Auth | B15: JWT middleware, RBAC, subscriber health endpoint | C15: Week 10
A16: 📊 Revenue + Franchise | B16: Reconciliation, forecast, LCO commission | C16: Week 11
A17: 🌐 Portal | B17: Subscriber self-service web portal | C17: Week 12
... A20: 📎 Prompt Snippets | B20: Reusable context blocks to paste into LM Studio | C20: Every session
A22: COLUMN GUIDE — main task sheets
A24: Column | B24: Meaning | C24: Notes
A25: Session ID | B25: Unique identifier for each LM Studio chat session | C25: Format: MOD-NNN (e.g. DB-001, AAA-003)
A26: Phase / Week | B26: Which development week this belongs to | C26: Follow in order — later phases depend on earlier ones
A27: Task Title | B27: What this session produces | C27: One function or one file per session
A28: FR IDs | B28: Which requirements this satisfies | C28: Trace back to SRS Doc 02
A29: Doc Reference | B29: Which DDS/DBD/MDS section to read before starting | C29: Always read before opening LM Studio
A30: Prerequisites | B30: Sessions that MUST be complete before starting this one | C30: Red if not met → do not proceed
A31: Model | B31: Which LM Studio model to use | C31: Qwen3-14B-Q4 default; Llama3.3-8B for speed-only tasks
A32: Context Tokens (est.) | B32: Estimated tokens this session will consume | C32: Stay under 8,000 total
A33: System Block | B33: The system prompt preamble to paste first | C33: Always the same base block + FR
A34: LM Studio Prompt | B34: Exact prompt to paste after the system block | C34: Do not paraphrase — paste verbatim
A35: Test You Write First | B35: The Go test to write BEFORE opening LM Studio | C35: Run it — confirm it FAILS first
... A42: Notes | B42: Free-form notes | C42: Document deviations from expected output
A44: THE THREE RULES (never break these)
A46: Rule 1 | B46: YOU write the test. The MODEL writes the implementation. | C46: Never ask model to write test AND implementation in same session
A47: Rule 2 | B47: One function per session. Reset session on 2nd consecutive failure. | C47: Fresh context = better output
A48: Rule 3 | B48: Use Claude for architecture decisions. LM Studio for code generation. | C48: Hybrid approach — Claude is free in this chat
A50: CONTEXT BUDGET PER SESSION
A51: System block | B51: ~500 tokens | C51: Always included
A52: FR spec (1 FR) | B52: ~100 tokens | C52: Paste only the relevant FR line
A53: DDS scaffold | B53: ~400 tokens | C53: Paste only the relevant function scaffold
A54: Your test | B54: ~300 tokens | C54: Paste the failing test
A55: REMAINING BUDGET | B55: ~6,700 tokens | C55: The model's actual working space
A56: RESPONSE | B56: ~1,500 tokens | C56: Ask for one function at a time
A58: MODEL COLOUR LEGEND
A59: Teal / light green cell in Model column | B59: =Llama3.1-8B-Q5_K_M (~5 GB VRAM — load when Docker stack runs simultaneously)
A60: White / default cell in Model column | B60: =Qwen3-14B-Q4_K_M (~9.1 GB VRAM at 4k ctx — load for reasoning-heavy sessions)

Sheet ✅ Definition of Done
A1: DEFINITION OF DONE — every task must pass ALL checks in its category before status → Done
A2: Check ID | B2: Category | C2: Exact Verification Step | D2: Command / Action | E2: Tool | F2: Expected Result | G2: Your Result | H2: Pass? (Y/N/NA)
A3: ▸ 0 · Every Task
A4: L0-001 | B4: 0 · Every Task | C4: Test written by YOU before LM Studio opened | D4: git log --oneline | head -5 → test file committed before impl file | E4: git | F4: Test commit timestamp < impl commit timestamp
A5: L0-002 | B5: 0 · Every Task | C5: Test FAILS before implementation (red phase confirmed) | D5: go test -run {TestName} ./... → run BEFORE pasting model output | E5: go test | F5: FAIL: undefined or compile error
A6: L0-003 | B6: 0 · Every Task | C6: go build passes with zero errors | D6: go build ./... | E6: go | F6: Exit code 0, no output
A7: L0-004 | B7: 0 · Every Task | C7: go vet passes with zero warnings | D7: go vet ./... | E7: go | F7: Exit code 0, no output
A8: L0-005 | B8: 0 · Every Task | C8: Race detector clean — run 3 times | D8: go test -race -count=3 ./internal/{module}/... | E8: go test | F8: ok (0 data races) × 3 runs
A9: L0-006 | B9: 0 · Every Task | C9: golangci-lint clean | D9: golangci-lint run --enable=errcheck,gosec,staticcheck ./... | E9: golangci-lint | F9: No issues found.
A10: L0-007 | B10: 0 · Every Task | C10: No float64 used for money anywhere in this file | D10: grep -n "float64\|math.Round\|Sprintf.*%.2f" internal/{module}/*.go | E10: grep | F10: Zero matches
A11: L0-008 | B11: 0 · Every Task | C11: No plaintext PII in any log statement | D11: grep -rni "aadhaar\|\.pan\b\|mobile_number" --include="*.go" internal/{module}/ | grep "log\." | E11: grep | F11: Zero matches
A12: L0-009 | B12: 0 · Every Task | C12: Pre-commit hook passes on staged files | D12: git add -p && git commit --dry-run | E12: git | F12: pre-commit exits 0 (no PII leak detected)
A13: L0-010 | B13: 0 · Every Task | C13: Conventional commit message format used | D13: git log -1 --format=%s | E13: git | F13: Starts with feat()|fix()|test()|db:|chore:|refactor()
A14: ▸ 1 · DB Migration
A15: L1-001 | B15: 1 · DB Migration | C15: Migration applies cleanly on empty DB | D15: goose -dir ./migrations postgres "$DSN" up | E15: goose | F15: OK migrations/NNNN_tablename.sql
A16: L1-002 | B16: 1 · DB Migration | C16: Migration rolls back cleanly (Down works) | D16: goose -dir ./migrations postgres "$DSN" down && goose ... up | E16: goose | F16: OK for both down and re-up
A17: L1-003 | B17: 1 · DB Migration | C17: All columns match DBD §6.2 exactly (type, nullable, default) | D17: psql -c "\d+ {table_name}" → compare with DBD §6.2 | E17: psql | F17: Every column type matches spec exactly
A18: L1-004 | B18: 1 · DB Migration | C18: All indexes from DBD §6.4 exist | D18: psql -c "\di+ {table_name}*" | E18: psql | F18: Each index listed in DBD §6.4 is present
A19: L1-005 | B19: 1 · DB Migration | C19: INCLUDE clause correct on LEA / CGNAT indexes | D19: psql -c "SELECT indexdef FROM pg_indexes WHERE indexname='idx_lea_ipv4_time';" | E19: psql | F19: INCLUDE (subscriber_id, stop_time) present
A20: L1-006 | B20: 1 · DB Migration | C20: Constraints enforced — insert violating row and confirm rejection | D20: psql -c "INSERT INTO invoices(cgst_amount,igst_amount,...) VALUES(71.91,143.82,...);" | E20: psql | F20: ERROR 23514 constraint violation
A21: L1-007 | B21: 1 · DB Migration | C21: Partitioned tables have ≥ 3 future partitions | D21: psql -c "SELECT tablename FROM pg_tables WHERE tablename LIKE '{table}%';" | E21: psql | F21: Parent + ≥3 monthly partition tables listed
A22: L1-008 | B22: 1 · DB Migration | C22: FK constraints enforced — insert orphan row and confirm rejection | D22: psql -c "INSERT INTO subscribers(plan_id) VALUES(9999999);" | E22: psql | F22: ERROR 23503 foreign key violation
A23: L1-009 | B23: 1 · DB Migration | C23: Row security on lea_audit_log blocks UPDATE | D23: psql -c "UPDATE lea_audit_log SET accessor_identity='x' WHERE 1=1;" | E23: psql | F23: ERROR: permission denied or 0 rows updated
A24: ▸ 2 · Unit Tests
A25: L2-001 | B25: 2 · Unit Tests | C25: Every FR for this module has ≥1 named test: TestFR_{ID}_... | D25: grep -r "func Test" internal/{module}/ | grep -c "FR_" | E25: grep | F25: Count ≥ number of FRs for this module
A26: L2-002 | B26: 2 · Unit Tests | C26: Coverage ≥ 80% (≥90% for crypto and middleware) | D26: go test -coverprofile=cov.out ./internal/{module}/... && go tool cover -func cov.out | tail -1 | E26: go test | F26: total: statements XX.X% → meets threshold
A27: L2-003 | B27: 2 · Unit Tests | C27: Happy path test passes | D27: go test -race -v -run Test{FunctionName}_HappyPath ./... | E27: go test | F27: --- PASS
A28: L2-004 | B28: 2 · Unit Tests | C28: Error / rejection path test passes | D28: go test -race -v -run Test{FunctionName}_Invalid ./... | E28: go test | F28: --- PASS (error returned as expected)
A29: L2-005 | B29: 2 · Unit Tests | C29: Edge case: zero / nil / empty input handled without panic | D29: go test -race -v -run Test{FunctionName}_Edge ./... | E29: go test | F29: --- PASS or error returned; never panic
A30: L2-006 | B30: 2 · Unit Tests | C30: Decimal precision verified to 2dp (billing module only) | D30: go test -v -run TestCalculateGst ./internal/billing/ | grep PASS | E30: go test | F30: Exact string values: 71.91 not 71.9099...
A31: ▸ 3 · Integration
A32: L3-001 | B32: 3 · Integration | C32: Docker stack healthy before running integration tests | D32: docker compose ps → all containers healthy | E32: docker | F32: All 8 containers: healthy / running
A33: L3-002 | B33: 3 · Integration | C33: Integration test suite passes with -tags=integration | D33: go test -race -tags=integration -v ./... | E33: go test | F33: All INT-* tests PASS
A34: L3-003 | B34: 3 · Integration | C34: Redis actually used on hot path (no PostgreSQL fallback hit for cached subscriber) | D34: redis-cli monitor & → run auth test → grep for "HGET subscriber:" | E34: redis-cli | F34: HGET subscriber:{username} appears in monitor output
A35: L3-004 | B35: 3 · Integration | C35: Asynq task actually enqueued in correct queue | D35: asynq task ls --queue {queue_name} --state pending → after trigger | E35: asynq CLI | F35: Task of correct type appears in queue
A36: L3-005 | B36: 3 · Integration | C36: notification_log row created for every dispatch attempt | D36: psql -c "SELECT COUNT(*) FROM notification_log WHERE subscriber_id={id};" | E36: psql | F36: Count matches number of dispatch calls made in test
A37: L3-006 | B37: 3 · Integration | C37: Idempotency: same transaction_token called twice = same TX ID, single credit | D37: go test -tags=integration -run TestWalletRecharge_Idempotent ./... | E37: go test | F37: tx1.ID == tx2.ID AND balance = single plan price
A38: L3-007 | B38: 3 · Integration | C38: DND subscriber gets suppressed_dnd in notification_log | D38: go test -tags=integration -run TestDispatcher_DND ./... | E38: go test | F38: delivery_status = suppressed_dnd in DB row
A39: L3-008 | B39: 3 · Integration | C39: Webhook HMAC: invalid signature returns 400, no state change | D39: go test -tags=integration -run TestWebhookHMAC_InvalidSignatureRejected ./... | E39: go test | F39: HTTP 400 | wallet balance unchanged
A40: ▸ 4 · Security
A41: L4-001 | B41: 4 · Security | C41: PII scan: zero plaintext Aadhaar/PAN in entire codebase | D41: grep -rni "aadhaar\|\.pan\b" --include="*.go" . | grep -v "_test\|encrypt\|db\." | grep "log\." | E41: grep | F41: Zero matches
A42: L4-002 | B42: 4 · Security | C42: PII scan: zero plaintext PII in DB column values | D42: psql -c "SELECT aadhaar_encrypted FROM kyc_verifications LIMIT 5;" → all values start with v | E42: psql | F42: All values have format vN:base64...
A43: L4-003 | B43: 4 · Security | C43: AES ciphertext is non-deterministic (same input ≠ same output) | D43: go test -v -run TestEncrypt_NonDeterministic ./pkg/crypto/ | E43: go test | F43: Two encryptions of same string produce different ciphertexts
A44: L4-004 | B44: 4 · Security | C44: Cross-rotation decryption works (v1 ciphertext after v2 rotation) | D44: go test -v -run TestDecrypt_CrossKeyVersion ./pkg/crypto/ | E44: go test | F44: PASS — plaintext restored correctly
A45: L4-005 | B45: 4 · Security | C45: JWT middleware rejects expired token with 401 | D45: go test -v -run TestJWT_ExpiredToken ./internal/middleware/ | E45: go test | F45: HTTP 401 returned
A46: L4-006 | B46: 4 · Security | C46: Wrong role returns 403 (not 401 or 200) | D46: go test -v -run TestRequireRole_WrongRole ./internal/middleware/ | E46: go test | F46: HTTP 403 returned
A47: L4-007 | B47: 4 · Security | C47: HMAC comparison uses hmac.Equal (timing-safe), not == | D47: grep -n "hmac.Equal" internal/billing/webhook.go | E47: grep | F47: Line found using hmac.Equal
A48: L4-008 | B48: 4 · Security | C48: Webhook HMAC validated on raw []byte BEFORE json.Unmarshal | D48: grep -n "Unmarshal" internal/billing/webhook.go → line number > HMAC check line | E48: grep | F48: Unmarshal line number > ValidateRazorpaySignature line number
A49: L4-009 | B49: 4 · Security | C49: gosec static analysis clean for this module | D49: gosec ./internal/{module}/... | E49: gosec | F49: No issues found
A50: L4-010 | B50: 4 · Security | C50: LEA audit log is append-only (UPDATE blocked at DB level) | D50: psql -c "UPDATE lea_audit_log SET accessor_identity='hack' WHERE 1=1;" | E50: psql | F50: ERROR or 0 rows updated
A51: ▸ 5 · Notifications
A52: L5-001 | B52: 5 · Notifications | C52: WhatsApp send uses template message type (not freeform text) | D52: grep -n '"type": "template"' internal/notifications/whatsapp.go | E52: grep | F52: Line found with template type in payload
A53: L5-002 | B53: 5 · Notifications | C53: provider_message_id saved to notification_log after WhatsApp send | D53: go test -tags=integration -run TestWhatsApp_SendTemplate_LogsProviderID ./... | E53: go test | F53: notification_log.provider_message_id non-empty
A54: L5-003 | B54: 5 · Notifications | C54: Meta delivery webhook updates notification_log.delivery_status | D54: go test -tags=integration -run TestWhatsAppWebhook_UpdatesDeliveryStatus ./... | E54: go test | F54: delivery_status changes from sent → delivered
A55: L5-004 | B55: 5 · Notifications | C55: Meta webhook HMAC verified via X-Hub-Signature-256 header | D55: grep -n "X-Hub-Signature-256" internal/notifications/webhook.go | E55: grep | F55: Header read and verified before any DB operation
A56: L5-005 | B56: 5 · Notifications | C56: DND check fires BEFORE any API call (not after) | D56: grep -n "dnd_opt_out\|DndOptOut" internal/notifications/dispatcher.go | E56: grep | F56: DND check line number < WhatsApp client call line number
A57: L5-006 | B57: 5 · Notifications | C57: All 8 templates (TMPL-001..008) registered in notification_templates table | D57: psql -c "SELECT COUNT(*) FROM notification_templates;" | E57: psql | F57: 8
A58: L5-007 | B58: 5 · Notifications | C58: E.164 phone number format validated before SMS send | D58: go test -v -run TestSMS_InvalidPhoneRejected ./internal/notifications/ | E58: go test | F58: Error returned for non-E.164 number
A59: L5-008 | B59: 5 · Notifications | C59: Dispatch latency ≤ 5s from Asynq task dequeue to notification_log.sent_at | D59: go test -tags=integration -run TestFUPWarningTask_E2ELatency ./internal/tasks/ | E59: go test | F59: sent_at - task_dequeued_at < 5 seconds
A60: ▸ 6 · Performance
A61: L6-001 | B61: 6 · Performance | C61: RADIUS auth p99 ≤ 15ms at 5,000 req/s (NFR-PERF-001) | D61: radperf --rate 5000 --duration 600 → read p99 line | E61: radperf | F61: p99_latency_ms < 15
A62: L6-002 | B62: 6 · Performance | C62: API p99 ≤ 200ms at 500 concurrent users (NFR-PERF-002) | D62: k6 run --vus 500 --duration 5m scripts/k6_api_load.js | E62: k6 | F62: http_req_duration p(99) < 200ms
A63: L6-003 | B63: 6 · Performance | C63: Unbilled report runs in ≤ 60s for 20k subscribers (NFR-BIZ-001) | D63: time psql -c "SELECT COUNT(*) FROM subscribers s LEFT JOIN invoices..." | E63: psql | F63: real time < 60s | EXPLAIN uses idx_revenue_unbilled
A64: L6-004 | B64: 6 · Performance | C64: Redis Sentinel failover ≤ 3s (NFR-AVAIL-001) | D64: docker compose stop redis_primary → watch redis-cli -p 26379 sentinel master bss_master | E64: docker/redis-cli | F64: New master IP appears within 3 seconds
A65: L6-005 | B65: 6 · Performance | C65: No goroutine leak after 1h hold at 20k sessions (NFR-SCAL-001) | D65: curl http://localhost:9100/debug/pprof/goroutine?debug=1 | head -5 → after load test | E65: pprof | F65: Goroutine count stable (not growing) throughout hold
A66: L6-006 | B66: 6 · Performance | C66: TLS 1.3 minimum, TLS 1.2 disabled (NFR-SEC-001) | D66: testssl.sh --protocols https://localhost:8443 | E66: testssl.sh | F66: TLS 1.3 YES | TLS 1.2 NO or disabled
A67: ▸ 7 · Git Hygiene
A68: L7-001 | B68: 7 · Git Hygiene | C68: Commit message follows conventional format | D68: git log -1 --format=%s | E68: git | F68: feat(module): SESSION-ID description
A69: L7-002 | B69: 7 · Git Hygiene | C69: No .env or secret files committed | D69: git log --all --full-history -- ".env" "*.key" "*.pem" | E69: git | F69: Empty output (no secrets in history)
A70: L7-003 | B70: 7 · Git Hygiene | C70: go.mod and go.sum both committed | D70: git status go.mod go.sum | E70: git | F70: Both files committed (not in untracked or modified)
A71: L7-004 | B71: 7 · Git Hygiene | C71: Migration files are numbered sequentially with no gaps | D71: ls migrations/ | sort | E71: ls | F71: Sequential NNNNNNNNNNNN_*.sql with no gaps
A72: ▸ 8 · Sign-Off
A73: L8-001 | B73: 8 · Sign-Off | C73: Tracker status column updated to Done | D73: Open tracker sheet for this task → Status = Done | E73: Manual | F73: Status cell = Done
A74: L8-002 | B74: 8 · Sign-Off | C74: All prerequisite tasks are also Done (no orphaned deps) | D74: Check Prerequisites column in tracker → all listed session IDs = Done | E74: Manual | F74: All prerequisite sessions show Done in tracker
A75: L8-003 | B75: 8 · Sign-Off | C75: Notes column updated with any deviations from expected output | D75: Open tracker Notes column for this session | E75: Manual | F75: Either empty (no deviations) or deviation documented
A76: L8-004 | B76: 8 · Sign-Off | C76: Corresponding INT-* test row marked Done in 🧪 Integration Tests sheet | D76: Open 🧪 Integration Tests sheet → find matching INT-* row | E76: Manual | F76: INT-* Status = Done
A77: L0-011
A78: Total checks: 66 | Rule: ALL applicable checks must be Y or NA before marking task Done | G78: Y count: | H78: =COUNTIF(H3:H76,"Y")

Sheet 📊 Progress Dashboard
A1: BSS/OSS DEVELOPMENT PROGRESS DASHBOARD
A2: Auto-calculated from Status columns in each task sheet — update Status cells to see progress
A4: Module / Sheet | B4: Total Tasks | C4: Done | D4: In Progress | E4: Blocked | F4: % Complete | G4: Status Bar | H4: Next Unfinished Task
A5: 🔧 Environment Setup | B5: 9 | C5: =COUNTIF('🔧 Environment Setup'!P:P,"Done") | D5: =COUNTIF('🔧 Environment Setup'!P:P,"In Progress") | E5: =COUNTIF('🔧 Environment Setup'!P:P,"Blocked") | F5: =IFERROR(C5/B5,0) | G5: =IFERROR(REPT("█",ROUND(C5/B5*20,0))&REPT("░",20-ROUND(C5/B5*20,0)),"░░░░░░░░░░░░░░░░░░░░") | H5: =IFERROR(INDEX('🔧 Environment Setup'!C:C,MATCH(FALSE,EXACT('🔧 Environment Setup'!P:P,"Done"),0)),"✅ All Done!")
A6: 🗄️ DB Migrations | B6: 15 | C6: =COUNTIF('🗄️ DB Migrations'!P:P,"Done") | D6: =COUNTIF('🗄️ DB Migrations'!P:P,"In Progress") | E6: =COUNTIF('🗄️ DB Migrations'!P:P,"Blocked") | F6: =IFERROR(C6/B6,0) | G6: =IFERROR(REPT("█",ROUND(C6/B6*20,0))&REPT("░",20-ROUND(C6/B6*20,0)),"░░░░░░░░░░░░░░░░░░░░") | H6: =IFERROR(INDEX('🗄️ DB Migrations'!C:C,MATCH(FALSE,EXACT('🗄️ DB Migrations'!P:P,"Done"),0)),"✅ All Done!")
A7: 🔐 Crypto Module | B7: 4 | C7: =COUNTIF('🔐 Crypto Module'!P:P,"Done") | D7: =COUNTIF('🔐 Crypto Module'!P:P,"In Progress") | E7: =COUNTIF('🔐 Crypto Module'!P:P,"Blocked") | F7: =IFERROR(C7/B7,0) | G7: =IFERROR(REPT("█",ROUND(C7/B7*20,0))&REPT("░",20-ROUND(C7/B7*20,0)),"░░░░░░░░░░░░░░░░░░░░") | H7: =IFERROR(INDEX('🔐 Crypto Module'!C:C,MATCH(FALSE,EXACT('🔐 Crypto Module'!P:P,"Done"),0)),"✅ All Done!")
A8: 📡 RADIUS AAA | B8: 5 | C8: =COUNTIF('📡 RADIUS AAA'!P:P,"Done") | D8: =COUNTIF('📡 RADIUS AAA'!P:P,"In Progress") | E8: =COUNTIF('📡 RADIUS AAA'!P:P,"Blocked") | F8: =IFERROR(C8/B8,0) | G8: =IFERROR(REPT("█",ROUND(C8/B8*20,0))&REPT("░",20-ROUND(C8/B8*20,0)),"░░░░░░░░░░░░░░░░░░░░") | H8: =IFERROR(INDEX('📡 RADIUS AAA'!C:C,MATCH(FALSE,EXACT('📡 RADIUS AAA'!P:P,"Done"),0)),"✅ All Done!")
A9: 💳 Billing Module | B9: 6 | C9: =COUNTIF('💳 Billing Module'!P:P,"Done") | D9: =COUNTIF('💳 Billing Module'!P:P,"In Progress") | E9: =COUNTIF('💳 Billing Module'!P:P,"Blocked") | F9: =IFERROR(C9/B9,0) | G9: =IFERROR(REPT("█",ROUND(C9/B9*20,0))&REPT("░",20-ROUND(C9/B9*20,0)),"░░░░░░░░░░░░░░░░░░░░") | H9: =IFERROR(INDEX('💳 Billing Module'!C:C,MATCH(FALSE,EXACT('💳 Billing Module'!P:P,"Done"),0)),"✅ All Done!")
A10: 🔔 Notifications | B10: 5 | C10: =COUNTIF('🔔 Notifications'!P:P,"Done") | D10: =COUNTIF('🔔 Notifications'!P:P,"In Progress") | E10: =COUNTIF('🔔 Notifications'!P:P,"Blocked") | F10: =IFERROR(C10/B10,0) | G10: =IFERROR(REPT("█",ROUND(C10/B10*20,0))&REPT("░",20-ROUND(C10/B10*20,0)),"░░░░░░░░░░░░░░░░░░░░") | H10: =IFERROR(INDEX('🔔 Notifications'!C:C,MATCH(FALSE,EXACT('🔔 Notifications'!P:P,"Done"),0)),"✅ All Done!")
A11: ⚡ FUP + Asynq | B11: 3 | C11: =COUNTIF('⚡ FUP + Asynq'!P:P,"Done") | D11: =COUNTIF('⚡ FUP + Asynq'!P:P,"In Progress") | E11: =COUNTIF('⚡ FUP + Asynq'!P:P,"Blocked") | F11: =IFERROR(C11/B11,0) | G11: =IFERROR(REPT("█",ROUND(C11/B11*20,0))&REPT("░",20-ROUND(C11/B11*20,0)),"░░░░░░░░░░░░░░░░░░░░") | H11: =IFERROR(INDEX('⚡ FUP + Asynq'!C:C,MATCH(FALSE,EXACT('⚡ FUP + Asynq'!P:P,"Done"),0)),"✅ All Done!")
A12: 🔑 API + Auth | B12: 4 | C12: =COUNTIF('🔑 API + Auth'!P:P,"Done") | D12: =COUNTIF('🔑 API + Auth'!P:P,"In Progress") | E12: =COUNTIF('🔑 API + Auth'!P:P,"Blocked") | F12: =IFERROR(C12/B12,0) | G12: =IFERROR(REPT("█",ROUND(C12/B12*20,0))&REPT("░",20-ROUND(C12/B12*20,0)),"░░░░░░░░░░░░░░░░░░░░") | H12: =IFERROR(INDEX('🔑 API + Auth'!C:C,MATCH(FALSE,EXACT('🔑 API + Auth'!P:P,"Done"),0)),"✅ All Done!")
A13: 📊 Revenue + Franchise | B13: 5 | C13: =COUNTIF('📊 Revenue + Franchise'!P:P,"Done") | D13: =COUNTIF('📊 Revenue + Franchise'!P:P,"In Progress") | E13: =COUNTIF('📊 Revenue + Franchise'!P:P,"Blocked") | F13: =IFERROR(C13/B13,0) | G13: =IFERROR(REPT("█",ROUND(C13/B13*20,0))&REPT("░",20-ROUND(C13/B13*20,0)),"░░░░░░░░░░░░░░░░░░░░") | H13: =IFERROR(INDEX('📊 Revenue + Franchise'!C:C,MATCH(FALSE,EXACT('📊 Revenue + Franchise'!P:P,"Done"),0)),"✅ All Done!")
A14: 🌐 Portal | B14: 4 | C14: =COUNTIF('🌐 Portal'!P:P,"Done") | D14: =COUNTIF('🌐 Portal'!P:P,"In Progress") | E14: =COUNTIF('🌐 Portal'!P:P,"Blocked") | F14: =IFERROR(C14/B14,0) | G14: =IFERROR(REPT("█",ROUND(C14/B14*20,0))&REPT("░",20-ROUND(C14/B14*20,0)),"░░░░░░░░░░░░░░░░░░░░") | H14: =IFERROR(INDEX('🌐 Portal'!C:C,MATCH(FALSE,EXACT('🌐 Portal'!P:P,"Done"),0)),"✅ All Done!")
A15: 🧪 Integration Tests | B15: 34 | C15: =COUNTIF('🧪 Integration Tests'!I:I,"Done") | D15: =COUNTIF('🧪 Integration Tests'!I:I,"In Progress") | E15: =COUNTIF('🧪 Integration Tests'!I:I,"Blocked") | F15: =IFERROR(C15/B15,0) | G15: =IFERROR(REPT("█",ROUND(C15/B15*20,0))&REPT("░",20-ROUND(C15/B15*20,0)),"░░░░░░░░░░░░░░░░░░░░") | H15: =IFERROR(INDEX('🧪 Integration Tests'!C:C,MATCH(FALSE,EXACT('🧪 Integration Tests'!I:I,"Done"),0)),"✅ All Done!")
A16: ⚡ NFR Load Tests | B16: 8 | C16: =COUNTIF('⚡ NFR Load Tests'!I:I,"Done") | D16: =COUNTIF('⚡ NFR Load Tests'!I:I,"In Progress") | E16: =COUNTIF('⚡ NFR Load Tests'!I:I,"Blocked") | F16: =IFERROR(C16/B16,0) | G16: =IFERROR(REPT("█",ROUND(C16/B16*20,0))&REPT("░",20-ROUND(C16/B16*20,0)),"░░░░░░░░░░░░░░░░░░░░") | H16: =IFERROR(INDEX('⚡ NFR Load Tests'!C:C,MATCH(FALSE,EXACT('⚡ NFR Load Tests'!I:I,"Done"),0)),"✅ All Done!")
A17: TOTAL | B17: =SUM(B5:B16) | C17: =SUM(C5:C16) | D17: =SUM(D5:D16) | E17: =SUM(E5:E16) | F17: =IFERROR(C17/B17,0)
A19: DoD Checks Passed (Y): | D19: ='✅ Definition of Done'!H77 | E19: of 65 total checks — all must be Y or NA before declaring 100% Done
A21: QUICK VERIFICATION COMMANDS — run these after every session to confirm Done
A22: When to run | B22: Command | C22: Expected output
A23: Every session | B23: go build ./... && go vet ./... && go test -race -count=3 ./internal/{module}/... | C23: All pass, 0 races
A24: Every session | B24: golangci-lint run --enable=errcheck,gosec,staticcheck ./... | C24: No issues found.
A25: Every session | B25: grep -rni "aadhaar|\.pan\b" --include="*.go" . | grep -v "_test\|encrypt" | grep "log\." | C25: Zero matches
A26: DB migrations | B26: goose -dir ./migrations postgres "$DSN" status | C26: All: Applied
A27: DB migrations | B27: psql -c "\d+ {table_name}" | C27: Columns match DBD §6.2
A28: Integration tests | B28: docker compose ps && go test -race -tags=integration -v ./... | C28: All INT-* PASS
A29: Billing module | B29: grep -n "float64" internal/billing/*.go | C29: Zero matches
A30: After every commit | B30: git log -1 --format="%H %s" | C30: Hash + conventional message
A31: Security check | B31: gosec ./internal/{module}/... | C31: No issues found
A32: WhatsApp | B32: psql -c "SELECT COUNT(*) FROM notification_log WHERE delivery_status='sent';" | C32: > 0 rows when test ran
A33: Before Done | B33: go test -coverprofile=cov.out ./... && go tool cover -func cov.out | tail -1 | C33: ≥80% (≥90% crypto/middleware)
A34: Load test gate | B34: radperf output: p99 ≤ 15ms | k6 output: p(99) < 200ms | C34: NFR thresholds met

Sheet 🔧 Environment Setup
A1: Session ID | B1: Phase/Week | C1: Task Title | D1: FR IDs | E1: Doc Reference | F1: Prerequisites | G1: Model | H1: Est. Context Tokens | I1: System Block (paste first) | J1: LM Studio Prompt (paste verbatim) | K1: Test You Write First (before LM Studio) | L1: Expected Output | M1: Verification Command | N1: Quality Gates | O1: Risk Flags | P1: Status | Q1: Commit Message | R1: Notes
A2: ENV-001 | B2: Week 0 | C2: Install Go 1.21 + verify | D2: — | E2: DXD §11.1 | F2: None | G2: N/A | H2: N/A | I2: You are a Go 1.21 backend engineer. Project: ISP BSS/OSS. Stack: Go 1.21, PostgreSQL 15, Redis 7.2 Sentinel, Asynq. Rules: no global state | all errors wrapped with fmt.Errorf | all DB calls use context.Context | decimal.Decimal for ALL money | never log plaintext PII (aadhaar/pan/mobile) | structured JSON logs via zerolog. Package naming: internal/{module}, pkg/{shared}. FR being implemented: [PASTE ONE FR LINE FROM SRS §2.1] DDS reference: [PASTE RELEVANT SCAFFOLD FROM DDS] | J2: N/A — manual step | K2: go version # must show go1.21.x | L2: go version go1.21.x linux/amd64 | M2: go version && go env GOPATH | N2: GOPATH set | go vet ./... on empty project = clean | O2: Wrong PATH — ensure /usr/local/go/bin in PATH | P2: Done | Q2: chore: Go 1.21 installed | R2: Verified: go1.26.5 windows/amd64 on host; tests run in golang:1.22 container
A3: ENV-002 | B3: Week 0 | C3: Install Docker + Docker Compose v2 | D3: — | E3: DXD §11.1 | F3: ENV-001 | G3: N/A | H3: N/A | I3: You are a Go 1.21 backend engineer. Project: ISP BSS/OSS. Stack: Go 1.21, PostgreSQL 15, Redis 7.2 Sentinel, Asynq. Rules: no global state | all errors wrapped with fmt.Errorf | all DB calls use context.Context | decimal.Decimal for ALL money | never log plaintext PII (aadhaar/pan/mobile) | structured JSON logs via zerolog. Package naming: internal/{module}, pkg/{shared}. FR being implemented: [PASTE ONE FR LINE FROM SRS §2.1] DDS reference: [PASTE RELEVANT SCAFFOLD FROM DDS] | J3: N/A — manual step | K3: docker compose version # must show v2.x | L3: Docker Compose version v2.x | M3: docker compose version && docker version | N3: docker ps returns empty (not error) | compose v2 not v1 | O3: docker-compose (v1) vs docker compose (v2) — must be v2 | P3: Done | Q3: chore: Docker v24+ and Compose v2 installed | R3: Verified: Docker 29.6.2 with Compose v2
A4: ENV-003 | B4: Week 0 | C4: Install LM Studio + download Qwen3-14B-Q4_K_M | D4: — | E4: Previous response §Step 1 | F4: ENV-001 | G4: N/A | H4: N/A | I4: You are a Go 1.21 backend engineer. Project: ISP BSS/OSS. Stack: Go 1.21, PostgreSQL 15, Redis 7.2 Sentinel, Asynq. Rules: no global state | all errors wrapped with fmt.Errorf | all DB calls use context.Context | decimal.Decimal for ALL money | never log plaintext PII (aadhaar/pan/mobile) | structured JSON logs via zerolog. Package naming: internal/{module}, pkg/{shared}. FR being implemented: [PASTE ONE FR LINE FROM SRS §2.1] DDS reference: [PASTE RELEVANT SCAFFOLD FROM DDS] | J4: N/A — GUI step: open LM Studio → search Qwen3-14B → download Q4_K_M variant | K4: LM Studio chat: 'Write hello world in Go' → model responds with valid Go | L4: func main() { fmt.Println("Hello, World!") } | M4: Manual: model responds in < 30 seconds on 12GB GPU | N4: VRAM usage shown in LM Studio ≤ 10GB | tokens/sec ≥ 5 | O4: Downloading wrong quantization — must be Q4_K_M not Q8 (too large for 12GB) | P4: Todo | Q4: N/A
A5: ENV-004 | B5: Week 0 | C5: Start LM Studio local server + verify OpenAI endpoint | D5: — | E5: IDD §8.1 | F5: ENV-003 | G5: N/A | H5: N/A | I5: You are a Go 1.21 backend engineer. Project: ISP BSS/OSS. Stack: Go 1.21, PostgreSQL 15, Redis 7.2 Sentinel, Asynq. Rules: no global state | all errors wrapped with fmt.Errorf | all DB calls use context.Context | decimal.Decimal for ALL money | never log plaintext PII (aadhaar/pan/mobile) | structured JSON logs via zerolog. Package naming: internal/{module}, pkg/{shared}. FR being implemented: [PASTE ONE FR LINE FROM SRS §2.1] DDS reference: [PASTE RELEVANT SCAFFOLD FROM DDS] | J5: N/A — GUI: Developer tab → toggle Start Server | K5: curl http://localhost:1234/v1/models | L5: JSON response listing Qwen3-14B model | M5: curl -s http://localhost:1234/v1/models | python3 -m json.tool | N5: HTTP 200 response | model ID present in JSON | O5: Firewall blocking port 1234 — add ufw allow 1234/tcp if needed | P5: Todo | Q5: N/A
A6: ENV-005 | B6: Week 0 | C6: Init Go module + project structure | D6: — | E6: DXD §11.2 | F6: ENV-001 | G6: N/A | H6: N/A | I6: You are a Go 1.21 backend engineer. Project: ISP BSS/OSS. Stack: Go 1.21, PostgreSQL 15, Redis 7.2 Sentinel, Asynq. Rules: no global state | all errors wrapped with fmt.Errorf | all DB calls use context.Context | decimal.Decimal for ALL money | never log plaintext PII (aadhaar/pan/mobile) | structured JSON logs via zerolog. Package naming: internal/{module}, pkg/{shared}. FR being implemented: [PASTE ONE FR LINE FROM SRS §2.1] DDS reference: [PASTE RELEVANT SCAFFOLD FROM DDS] | J6: N/A — manual: mkdir isp-bss-oss && cd isp-bss-oss go mod init github.com/yourorg/isp-bss-oss mkdir -p cmd/radiusd cmd/api internal/{radius,billing,fup,notifications,revenue,franchise,cgnat,health,middleware,tasks} pkg/crypto web/portal migrations | K6: go build ./... # should succeed on empty module | L6: Exit code 0, no errors | M6: go build ./... && go vet ./... | N6: go.mod exists | all directories created | go vet clean | O6: Module path must match import paths used in code | P6: Done | Q6: chore: init Go module and project layout
A7: ENV-006 | B7: Week 0 | C7: Add core Go dependencies | D7: — | E7: DXD §11.1 | F7: ENV-005 | G7: N/A | H7: N/A | I7: You are a Go 1.21 backend engineer. Project: ISP BSS/OSS. Stack: Go 1.21, PostgreSQL 15, Redis 7.2 Sentinel, Asynq. Rules: no global state | all errors wrapped with fmt.Errorf | all DB calls use context.Context | decimal.Decimal for ALL money | never log plaintext PII (aadhaar/pan/mobile) | structured JSON logs via zerolog. Package naming: internal/{module}, pkg/{shared}. FR being implemented: [PASTE ONE FR LINE FROM SRS §2.1] DDS reference: [PASTE RELEVANT SCAFFOLD FROM DDS] | J7: N/A — manual: go get layeh.com/radius@latest go get github.com/go-redis/redis/v9 go get github.com/jackc/pgx/v5 go get github.com/shopspring/decimal go get github.com/hibiken/asynq go get github.com/rs/zerolog go get github.com/golang-jwt/jwt/v5 go get github.com/stretchr/testify go get github.com/pressly/goose/v3/cmd/goose@latest | K7: go build ./... && go mod tidy | L7: go.sum populated, all deps resolved | M7: go build ./... && cat go.sum | wc -l # should be > 50 lines | N7: No replace directives needed | go mod tidy produces no changes | O7: layeh.com/radius may need manual version pin — check latest on pkg.go.dev | P7: Done | Q7: chore: add core dependencies to go.mod
A8: ENV-007 | B8: Week 0 | C8: Start Docker infrastructure stack | D8: — | E8: IDD §8.2 | F8: ENV-002 | G8: N/A | H8: N/A | I8: You are a Go 1.21 backend engineer. Project: ISP BSS/OSS. Stack: Go 1.21, PostgreSQL 15, Redis 7.2 Sentinel, Asynq. Rules: no global state | all errors wrapped with fmt.Errorf | all DB calls use context.Context | decimal.Decimal for ALL money | never log plaintext PII (aadhaar/pan/mobile) | structured JSON logs via zerolog. Package naming: internal/{module}, pkg/{shared}. FR being implemented: [PASTE ONE FR LINE FROM SRS §2.1] DDS reference: [PASTE RELEVANT SCAFFOLD FROM DDS] | J8: N/A — create .env from .env.example then: docker compose up -d postgres_primary redis_primary redis_replica_1 redis_replica_2 redis_sentinel_1 redis_sentinel_2 redis_sentinel_3 gotenberg_engine | K8: docker compose ps # all containers healthy | L8: All containers status = healthy or running | M8: docker compose ps && redis-cli -p 26379 sentinel master bss_master | N8: PostgreSQL responds to pg_isready | Redis Sentinel elected a master | Gotenberg returns 200 on /health | O8: Sentinel may take 10-15s to elect master — wait before testing | P8: Done | Q8: N/A
A9: ENV-008 | B9: Week 0 | C9: Install golangci-lint + pre-commit PII hook | D9: NFR-SEC-002 | E9: TST §13.5 | F9: ENV-005 | G9: N/A | H9: N/A | I9: You are a Go 1.21 backend engineer. Project: ISP BSS/OSS. Stack: Go 1.21, PostgreSQL 15, Redis 7.2 Sentinel, Asynq. Rules: no global state | all errors wrapped with fmt.Errorf | all DB calls use context.Context | decimal.Decimal for ALL money | never log plaintext PII (aadhaar/pan/mobile) | structured JSON logs via zerolog. Package naming: internal/{module}, pkg/{shared}. FR being implemented: [PASTE ONE FR LINE FROM SRS §2.1] DDS reference: [PASTE RELEVANT SCAFFOLD FROM DDS] | J9: N/A — manual: curl -sSfL https://raw.githubusercontent.com/golangci/golangci-lint/master/install.sh | sh -s -- -b $(go env GOPATH)/bin v1.55.2 cat > .git/hooks/pre-commit << 'EOF' #!/bin/sh grep -rni "aadhaar\|\.pan\b" --include="*.go" . | grep -v "_test.go\|encrypt\|db\." | grep "log\.\|Print" && echo "PII LEAK DETECTED" && exit 1 exit 0 EOF chmod +x .git/hooks/pre-commit | K9: golangci-lint version && echo 'test' > /tmp/t.go && .git/hooks/pre-commit | L9: golangci-lint version shown | hook exits 0 on clean code | M9: golangci-lint run ./... --timeout 2m # expect 'no issues found' on empty project | N9: Hook blocks commit when test file contains 'log.Info(aadhaar)' | O9: Hook path must be .git/hooks/pre-commit not pre-commit.sh | P9: Done | Q9: chore: add golangci-lint and PII pre-commit hook
A10: ENV-009 | B10: Week 0 | C10: Create compliance.sh — automated DoD verification script | D10: L0-003..L0-008 (DoD checks) | E10: TST §13.5, DoD Level 0 | F10: ENV-006 (Go installed), ENV-008 (golangci-lint installed) | G10: Llama3.1-8B-Q5_K_M | H10: ~3,000 | I10: You are a Go 1.21 backend engineer. Project: ISP BSS/OSS. Stack: Go 1.21, PostgreSQL 15, Redis 7.2 Sentinel, Asynq. Rules: no global state | all errors wrapped with fmt.Errorf | all DB calls use context.Context | decimal.Decimal for ALL money | never log plaintext PII (aadhaar/pan/mobile) | structured JSON logs via zerolog. Package naming: internal/{module}, pkg/{shared}. FR being implemented: [PASTE ONE FR LINE FROM SRS §2.1] DDS reference: [PASTE RELEVANT SCAFFOLD FROM DDS] | J10: System block (no FR needed — this is a tooling task, not application code). Generate scripts/compliance.sh — a Bash script that accepts one argument: the Go package path. Example usage: ./scripts/compliance.sh internal/billing The script must run these checks IN ORDER and exit 1 on first failure: 1. go build ./... Label: "BUILD" 2. go vet ./... Label: "VET" 3. go test -race -count=3 ./{package}/... Label: "RACE (×3)" 4. golangci-lint run --enable=errcheck,gosec,staticcheck ./{package}/... Label: "LINT" 5. grep -rn "float64\|math.Round\|fmt.Sprintf.*%.2f" {package}/*.go Label: "FLOAT64 CHECK" Pass = zero matches 6. grep -rni "aadhaar\|\.pan\b\|mobile_number" --include="*.go" {package}/ | grep -v "_test.go\|encrypt\|db\." | grep "log\." Label: "PII LOG CHECK" Pass = zero matches 7. go test -coverprofile=/tmp/cov.out ./{package}/... && go tool cover -func /tmp/cov.out | tail -1 Label: "COVERAGE" Print result — do not fail on coverage threshold (user checks manually) Print a coloured PASS (green) or FAIL (red) next to each label. Print a final summary line: "N/7 checks passed for {package}" Script must be executable (chmod +x) and use #!/usr/bin/env bash at the top. | K10: # Run against crypto module (should all pass after CRY-004): chmod +x scripts/compliance.sh ./scripts/compliance.sh pkg/crypto # Expected output format: # [PASS] BUILD # [PASS] VET # [PASS] RACE (×3) # [PASS] LINT # [PASS] FLOAT64 CHECK # [PASS] PII LOG CHECK # [PASS] COVERAGE: 91.3% # 7/7 checks passed for pkg/crypto | L10: scripts/compliance.sh file created. When run: coloured PASS/FAIL per check. Final line: "7/7 checks passed for {package}" | M10: chmod +x scripts/compliance.sh ./scripts/compliance.sh pkg/crypto # run on crypto module first ./scripts/compliance.sh internal/billing echo "Exit code: $?" # must be 0 for all passing | N10: Script exits 1 on first failure (not silently continues) | Float64 grep returns non-zero when float64 found | PII grep returns non-zero when log.Info(aadhaar) found | Coverage line printed but does not cause failure | Coloured output: green=PASS red=FAIL | O10: Model may use 'exit 0' at end regardless — must use 'exit 1' on failure | grep exit code is 1 when no match (pass) and 0 when match (fail) — logic is INVERTED for grep checks | Must handle packages with no .go files gracefully | P10: Done | Q10: chore(scripts): ENV-009 add compliance.sh automated DoD check runner | R10: Addresses DoD fatigue gap — 65 manual checks reduced to 1 command per session

Sheet 🗄️ DB Migrations
A1: Session ID | B1: Phase/Week | C1: Task Title | D1: FR IDs | E1: Doc Reference | F1: Prerequisites | G1: Model | H1: Est. Context Tokens | I1: System Block (paste first) | J1: LM Studio Prompt (paste verbatim) | K1: Test You Write First (before LM Studio) | L1: Expected Output | M1: Verification Command | N1: Quality Gates | O1: Risk Flags | P1: Status | Q1: Commit Message | R1: Notes
A2: DB-001 | B2: Week 1 | C2: Migration: franchises table | D2: FR-FRN-001 | E2: DBD §6.2 franchises | F2: ENV-007 | G2: Llama3.1-8B-Q5_K_M | H2: ~2,500 | I2: You are a Go 1.21 backend engineer. Project: ISP BSS/OSS. Stack: Go 1.21, PostgreSQL 15, Redis 7.2 Sentinel, Asynq. Rules: no global state | all errors wrapped with fmt.Errorf | all DB calls use context.Context | decimal.Decimal for ALL money | never log plaintext PII (aadhaar/pan/mobile) | structured JSON logs via zerolog. Package naming: internal/{module}, pkg/{shared}. FR being implemented: [PASTE ONE FR LINE FROM SRS §2.1] DDS reference: [PASTE RELEVANT SCAFFOLD FROM DDS] | J2: Generate a goose migration SQL file for the table below. PostgreSQL 15 syntax. Include +goose Up and +goose Down sections. In +goose Down, DROP TABLE CASCADE. Add ONLY the indexes listed — no extras. Use TIMESTAMPTZ not TIMESTAMP. Never use SERIAL for tables that will be partitioned — use BIGSERIAL. Table spec: [PASTE TABLE FROM DBD §6.2] Indexes: [PASTE INDEXES FOR THIS TABLE FROM DBD §6.4] | K2: psql -h localhost -U postgres -d isp_bss_oss -c '\d+ franchises' | L2: Table franchises exists with all columns | commission_rate_pct NUMERIC(5,2) NOT NULL | M2: goose -dir ./migrations postgres "$DSN" status | N2: goose status shows DB-001 = applied | \d+ shows correct types and NOT NULL constraints | O2: Model may use TEXT for commission_rate — must be NUMERIC(5,2) | P2: Done | Q2: db: add franchises table migration | R2: Switched to Llama3.1-8B (5GB VRAM) — frees 7GB for Docker stack. 8B is sufficient for boilerplate SQL generation.
A3: DB-002 | B3: Week 1 | C3: Migration: plans table | D3: FR-AAA-004, FR-FUP-001 | E3: DBD §6.2 plans | F3: DB-001 | G3: Llama3.1-8B-Q5_K_M | H3: ~2,500 | I3: You are a Go 1.21 backend engineer. Project: ISP BSS/OSS. Stack: Go 1.21, PostgreSQL 15, Redis 7.2 Sentinel, Asynq. Rules: no global state | all errors wrapped with fmt.Errorf | all DB calls use context.Context | decimal.Decimal for ALL money | never log plaintext PII (aadhaar/pan/mobile) | structured JSON logs via zerolog. Package naming: internal/{module}, pkg/{shared}. FR being implemented: [PASTE ONE FR LINE FROM SRS §2.1] DDS reference: [PASTE RELEVANT SCAFFOLD FROM DDS] | J3: Generate a goose migration SQL file for the table below. PostgreSQL 15 syntax. Include +goose Up and +goose Down sections. In +goose Down, DROP TABLE CASCADE. Add ONLY the indexes listed — no extras. Use TIMESTAMPTZ not TIMESTAMP. Never use SERIAL for tables that will be partitioned — use BIGSERIAL. Table spec: [PASTE TABLE FROM DBD §6.2] Indexes: [PASTE INDEXES FOR THIS TABLE FROM DBD §6.4] | K3: psql ... -c '\d+ plans' | L3: fup_threshold_bytes BIGINT | franchise_id FK nullable | price NUMERIC(12,2) | M3: goose ... status && psql -c "INSERT INTO plans(name,rate_limit_string,volume_gb,fup_threshold_bytes,price,validity_days) VALUES('test','10M/10M',10,10737418240,199.00,30);" | N3: FK to franchises exists | INSERT succeeds without franchise_id | O3: Model may forget FK to franchises — check carefully | P3: Done | Q3: db: add plans table migration | R3: Switched to Llama3.1-8B (5GB VRAM) — frees 7GB for Docker stack. 8B is sufficient for boilerplate SQL generation.
A4: DB-003 | B4: Week 1 | C4: Migration: subscribers table | D4: FR-AAA-001..004 | E4: DBD §6.2 subscribers | F4: DB-002 | G4: Llama3.1-8B-Q5_K_M | H4: ~3,000 | I4: You are a Go 1.21 backend engineer. Project: ISP BSS/OSS. Stack: Go 1.21, PostgreSQL 15, Redis 7.2 Sentinel, Asynq. Rules: no global state | all errors wrapped with fmt.Errorf | all DB calls use context.Context | decimal.Decimal for ALL money | never log plaintext PII (aadhaar/pan/mobile) | structured JSON logs via zerolog. Package naming: internal/{module}, pkg/{shared}. FR being implemented: [PASTE ONE FR LINE FROM SRS §2.1] DDS reference: [PASTE RELEVANT SCAFFOLD FROM DDS] | J4: Generate a goose migration SQL file for the table below. PostgreSQL 15 syntax. Include +goose Up and +goose Down sections. In +goose Down, DROP TABLE CASCADE. Add ONLY the indexes listed — no extras. Use TIMESTAMPTZ not TIMESTAMP. Never use SERIAL for tables that will be partitioned — use BIGSERIAL. Table spec: [PASTE TABLE FROM DBD §6.2] Indexes: [PASTE INDEXES FOR THIS TABLE FROM DBD §6.4] | K4: psql ... -c '\d+ subscribers' | L4: status VARCHAR(20) | dunning_state VARCHAR(20) DEFAULT 'active' | dnd_opt_out BOOLEAN DEFAULT FALSE | M4: psql -c "SELECT column_name,data_type,column_default FROM information_schema.columns WHERE table_name='subscribers' ORDER BY ordinal_position;" | N4: idx_sub_auth index created | idx_sub_expiry partial index created | username UNIQUE constraint | O4: Model may omit dunning_state column (new in v2) — verify it is present | P4: Done | Q4: db: add subscribers table migration | R4: Switched to Llama3.1-8B (5GB VRAM) — frees 7GB for Docker stack. 8B is sufficient for boilerplate SQL generation.
A5: DB-004 | B5: Week 1 | C5: Migration: encryption_keys table | D5: FR-SEC-002, FR-SEC-003 | E5: DBD §6.2 encryption_keys | F5: DB-003 | G5: Llama3.1-8B-Q5_K_M | H5: ~2,000 | I5: You are a Go 1.21 backend engineer. Project: ISP BSS/OSS. Stack: Go 1.21, PostgreSQL 15, Redis 7.2 Sentinel, Asynq. Rules: no global state | all errors wrapped with fmt.Errorf | all DB calls use context.Context | decimal.Decimal for ALL money | never log plaintext PII (aadhaar/pan/mobile) | structured JSON logs via zerolog. Package naming: internal/{module}, pkg/{shared}. FR being implemented: [PASTE ONE FR LINE FROM SRS §2.1] DDS reference: [PASTE RELEVANT SCAFFOLD FROM DDS] | J5: Generate a goose migration SQL file for the table below. PostgreSQL 15 syntax. Include +goose Up and +goose Down sections. In +goose Down, DROP TABLE CASCADE. Add ONLY the indexes listed — no extras. Use TIMESTAMPTZ not TIMESTAMP. Never use SERIAL for tables that will be partitioned — use BIGSERIAL. Table spec: [PASTE TABLE FROM DBD §6.2] Indexes: [PASTE INDEXES FOR THIS TABLE FROM DBD §6.4] | K5: psql ... -c '\d+ encryption_keys' | L5: version_id VARCHAR(10) UNIQUE | key_hash VARCHAR(64) | status VARCHAR(10) DEFAULT 'active' | M5: psql -c "INSERT INTO encryption_keys(version_id,key_hash) VALUES('v1','abc123');" | N5: version_id UNIQUE constraint enforced | INSERT succeeds | O5: Model may add key_material column — must NOT exist (stored in secret manager only) | P5: Done | Q5: db: add encryption_keys table migration | R5: Switched to Llama3.1-8B (5GB VRAM) — frees 7GB for Docker stack. 8B is sufficient for boilerplate SQL generation.
A6: DB-005 | B6: Week 1 | C6: Migration: kyc_verifications table | D6: FR-SEC-002, FR-SEC-003 | E6: DBD §6.2 kyc_verifications | F6: DB-004 | G6: Llama3.1-8B-Q5_K_M | H6: ~2,500 | I6: You are a Go 1.21 backend engineer. Project: ISP BSS/OSS. Stack: Go 1.21, PostgreSQL 15, Redis 7.2 Sentinel, Asynq. Rules: no global state | all errors wrapped with fmt.Errorf | all DB calls use context.Context | decimal.Decimal for ALL money | never log plaintext PII (aadhaar/pan/mobile) | structured JSON logs via zerolog. Package naming: internal/{module}, pkg/{shared}. FR being implemented: [PASTE ONE FR LINE FROM SRS §2.1] DDS reference: [PASTE RELEVANT SCAFFOLD FROM DDS] | J6: Generate a goose migration SQL file for the table below. PostgreSQL 15 syntax. Include +goose Up and +goose Down sections. In +goose Down, DROP TABLE CASCADE. Add ONLY the indexes listed — no extras. Use TIMESTAMPTZ not TIMESTAMP. Never use SERIAL for tables that will be partitioned — use BIGSERIAL. Table spec: [PASTE TABLE FROM DBD §6.2] Indexes: [PASTE INDEXES FOR THIS TABLE FROM DBD §6.4] | K6: psql ... -c '\d+ kyc_verifications' | L6: aadhaar_encrypted TEXT nullable | key_version_id FK → encryption_keys.version_id | M6: psql -c "INSERT INTO kyc_verifications(subscriber_id,key_version_id) VALUES(1,'v1');" | N6: FK to encryption_keys enforced | FK to subscribers enforced | O6: Model may store plaintext aadhaar — column must be TEXT named aadhaar_encrypted | P6: Done | Q6: db: add kyc_verifications table migration | R6: Switched to Llama3.1-8B (5GB VRAM) — frees 7GB for Docker stack. 8B is sufficient for boilerplate SQL generation.
A7: DB-006 | B7: Week 1 | C7: Migration: gst_rates + invoices tables | D7: FR-BIL-001, FR-BIL-007 | E7: DBD §6.2 invoices | F7: DB-003 | G7: Llama3.1-8B-Q5_K_M | H7: ~3,000 | I7: You are a Go 1.21 backend engineer. Project: ISP BSS/OSS. Stack: Go 1.21, PostgreSQL 15, Redis 7.2 Sentinel, Asynq. Rules: no global state | all errors wrapped with fmt.Errorf | all DB calls use context.Context | decimal.Decimal for ALL money | never log plaintext PII (aadhaar/pan/mobile) | structured JSON logs via zerolog. Package naming: internal/{module}, pkg/{shared}. FR being implemented: [PASTE ONE FR LINE FROM SRS §2.1] DDS reference: [PASTE RELEVANT SCAFFOLD FROM DDS] | J7: Generate a goose migration SQL file for the table below. PostgreSQL 15 syntax. Include +goose Up and +goose Down sections. In +goose Down, DROP TABLE CASCADE. Add ONLY the indexes listed — no extras. Use TIMESTAMPTZ not TIMESTAMP. Never use SERIAL for tables that will be partitioned — use BIGSERIAL. Table spec: [PASTE TABLE FROM DBD §6.2] Indexes: [PASTE INDEXES FOR THIS TABLE FROM DBD §6.4] IMPORTANT: also create gst_rates table (id,cgst_rate,sgst_rate,igst_rate,effective_from) and add chk_gst_logic constraint on invoices: (cgst_amount>0 AND igst_amount=0) OR (igst_amount>0 AND cgst_amount=0) OR (cgst_amount=0 AND igst_amount=0) | K7: psql -c "INSERT INTO invoices(subscriber_id,base_amount,cgst_amount,sgst_amount,igst_amount,total_amount,gst_rate_id,gb_included,gb_used) VALUES(1,799.00,71.91,71.91,0,942.82,1,3300,2847);" | L7: INSERT succeeds for valid intrastate invoice | M7: psql -c "INSERT INTO invoices(subscriber_id,base_amount,cgst_amount,sgst_amount,igst_amount,total_amount,gst_rate_id,gb_included,gb_used) VALUES(1,799.00,71.91,0,143.82,1014.73,1,3300,2847);" # MUST fail with constraint violation | N7: chk_gst_logic constraint blocks cgst + igst both non-zero | gb_included and gb_used columns present | O7: Model forgets chk_gst_logic constraint | forgets gb_included/gb_used columns | P7: Done | Q7: db: add gst_rates and invoices table migration | R7: Switched to Llama3.1-8B (5GB VRAM) — frees 7GB for Docker stack. 8B is sufficient for boilerplate SQL generation.
A8: DB-007 | B8: Week 1 | C8: Migration: wallet_ledgers table | D8: FR-BIL-003, FR-BIL-005, FR-REV-002 | E8: DBD §6.2 wallet_ledgers | F8: DB-003 | G8: Llama3.1-8B-Q5_K_M | H8: ~2,500 | I8: You are a Go 1.21 backend engineer. Project: ISP BSS/OSS. Stack: Go 1.21, PostgreSQL 15, Redis 7.2 Sentinel, Asynq. Rules: no global state | all errors wrapped with fmt.Errorf | all DB calls use context.Context | decimal.Decimal for ALL money | never log plaintext PII (aadhaar/pan/mobile) | structured JSON logs via zerolog. Package naming: internal/{module}, pkg/{shared}. FR being implemented: [PASTE ONE FR LINE FROM SRS §2.1] DDS reference: [PASTE RELEVANT SCAFFOLD FROM DDS] | J8: Generate a goose migration SQL file for the table below. PostgreSQL 15 syntax. Include +goose Up and +goose Down sections. In +goose Down, DROP TABLE CASCADE. Add ONLY the indexes listed — no extras. Use TIMESTAMPTZ not TIMESTAMP. Never use SERIAL for tables that will be partitioned — use BIGSERIAL. Table spec: [PASTE TABLE FROM DBD §6.2] Indexes: [PASTE INDEXES FOR THIS TABLE FROM DBD §6.4] | K8: psql -c "INSERT INTO wallet_ledgers(subscriber_id,entry_type,amount,balance_after,transaction_token) VALUES(1,'credit',799.00,799.00,'tok_test_001');" | L8: INSERT succeeds | M8: psql -c "INSERT INTO wallet_ledgers(subscriber_id,entry_type,amount,balance_after,transaction_token) VALUES(1,'credit',799.00,799.00,'tok_test_001');" # second insert MUST fail (unique token) | N8: UNIQUE constraint on transaction_token | partial index (WHERE token IS NOT NULL) created | O8: Model may make transaction_token NOT NULL — must be NULLABLE (cash payments have no token) | P8: Done | Q8: db: add wallet_ledgers table migration | R8: Switched to Llama3.1-8B (5GB VRAM) — frees 7GB for Docker stack. 8B is sufficient for boilerplate SQL generation.
A9: DB-008 | B9: Week 2 | C9: Migration: notification_templates + notification_log | D9: FR-NOTIF-009, FR-NOTIF-010, FR-NOTIF-011 | E9: DBD §6.2 notification_log | F9: DB-003 | G9: Llama3.1-8B-Q5_K_M | H9: ~3,000 | I9: You are a Go 1.21 backend engineer. Project: ISP BSS/OSS. Stack: Go 1.21, PostgreSQL 15, Redis 7.2 Sentinel, Asynq. Rules: no global state | all errors wrapped with fmt.Errorf | all DB calls use context.Context | decimal.Decimal for ALL money | never log plaintext PII (aadhaar/pan/mobile) | structured JSON logs via zerolog. Package naming: internal/{module}, pkg/{shared}. FR being implemented: [PASTE ONE FR LINE FROM SRS §2.1] DDS reference: [PASTE RELEVANT SCAFFOLD FROM DDS] | J9: Generate a goose migration SQL file for the table below. PostgreSQL 15 syntax. Include +goose Up and +goose Down sections. In +goose Down, DROP TABLE CASCADE. Add ONLY the indexes listed — no extras. Use TIMESTAMPTZ not TIMESTAMP. Never use SERIAL for tables that will be partitioned — use BIGSERIAL. Table spec: [PASTE TABLE FROM DBD §6.2] Indexes: [PASTE INDEXES FOR THIS TABLE FROM DBD §6.4] Create both notification_templates and notification_log tables. notification_log.provider_message_id needs an index for delivery callback lookups. notification_log uses BIGSERIAL pk. | K9: psql -c '\d+ notification_log' | L9: BIGSERIAL pk | delivery_status DEFAULT 'sent' | provider_message_id nullable | idx_notif_provider_id index | M9: psql -c "INSERT INTO notification_templates(id,channel,template_name,event_trigger) VALUES('TMPL-001','whatsapp','fup_warning','fup_warning');" | N9: idx_notif_subscriber index created | idx_notif_provider_id partial index created | FK to subscribers and notification_templates | O9: Model may make template_id NOT NULL on notification_log — must be NULLABLE (system events may not have template) | P9: Done | Q9: db: add notification_templates and notification_log migrations | R9: Switched to Llama3.1-8B (5GB VRAM) — frees 7GB for Docker stack. 8B is sufficient for boilerplate SQL generation.
A10: DB-009 | B10: Week 2 | C10: Migration: tickets table | D10: FR-SUB-004 | E10: DBD §6.2 tickets | F10: DB-003 | G10: Llama3.1-8B-Q5_K_M | H10: ~2,000 | I10: You are a Go 1.21 backend engineer. Project: ISP BSS/OSS. Stack: Go 1.21, PostgreSQL 15, Redis 7.2 Sentinel, Asynq. Rules: no global state | all errors wrapped with fmt.Errorf | all DB calls use context.Context | decimal.Decimal for ALL money | never log plaintext PII (aadhaar/pan/mobile) | structured JSON logs via zerolog. Package naming: internal/{module}, pkg/{shared}. FR being implemented: [PASTE ONE FR LINE FROM SRS §2.1] DDS reference: [PASTE RELEVANT SCAFFOLD FROM DDS] | J10: Generate a goose migration SQL file for the table below. PostgreSQL 15 syntax. Include +goose Up and +goose Down sections. In +goose Down, DROP TABLE CASCADE. Add ONLY the indexes listed — no extras. Use TIMESTAMPTZ not TIMESTAMP. Never use SERIAL for tables that will be partitioned — use BIGSERIAL. Table spec: [PASTE TABLE FROM DBD §6.2] Indexes: [PASTE INDEXES FOR THIS TABLE FROM DBD §6.4] | K10: psql -c '\d+ tickets' | L10: status DEFAULT 'open' | category constraint in (connectivity,billing,plan_change,other) | M10: psql -c "INSERT INTO tickets(subscriber_id,category,description) VALUES(1,'billing','test ticket');" | N10: Status CHECK constraint | category CHECK constraint | updated_at has trigger | O10: Model may forget updated_at trigger | P10: Done | Q10: db: add tickets table migration | R10: Switched to Llama3.1-8B (5GB VRAM) — frees 7GB for Docker stack. 8B is sufficient for boilerplate SQL generation.
A11: DB-010 | B11: Week 2 | C11: Migration: subscriber_session_history (partitioned) | D11: FR-NET-001, FR-NET-003 | E11: DBD §6.2 subscriber_session_history | F11: DB-003 | G11: Qwen3-14B-Q4_K_M | H11: ~3,000 | I11: You are a Go 1.21 backend engineer. Project: ISP BSS/OSS. Stack: Go 1.21, PostgreSQL 15, Redis 7.2 Sentinel, Asynq. Rules: no global state | all errors wrapped with fmt.Errorf | all DB calls use context.Context | decimal.Decimal for ALL money | never log plaintext PII (aadhaar/pan/mobile) | structured JSON logs via zerolog. Package naming: internal/{module}, pkg/{shared}. FR being implemented: [PASTE ONE FR LINE FROM SRS §2.1] DDS reference: [PASTE RELEVANT SCAFFOLD FROM DDS] | J11: Generate a goose migration SQL file for the table below. PostgreSQL 15 syntax. Include +goose Up and +goose Down sections. In +goose Down, DROP TABLE CASCADE. Add ONLY the indexes listed — no extras. Use TIMESTAMPTZ not TIMESTAMP. Never use SERIAL for tables that will be partitioned — use BIGSERIAL. Table spec: [PASTE TABLE FROM DBD §6.2] Indexes: [PASTE INDEXES FOR THIS TABLE FROM DBD §6.4] IMPORTANT: This table uses RANGE partitioning on start_time (monthly). Use pg_partman: SELECT partman.create_parent('public.subscriber_session_history','start_time','monthly',3). Include this in +goose Up. Also create idx_lea_ipv4_time and idx_nas_active_cleanup indexes. | K11: psql -c "SELECT tablename FROM pg_tables WHERE tablename LIKE 'subscriber_session_history%';" | L11: Parent table + at least 3 monthly partition tables | M11: psql -c "SELECT partman.check_parent('public.subscriber_session_history');" | N11: Partitions created | idx_lea_ipv4_time INCLUDE clause correct | Partial index WHERE stop_time IS NULL | O11: Model may skip INCLUDE clause on LEA index — must include subscriber_id and stop_time | P11: Done | Q11: db: add subscriber_session_history partitioned table migration | R11: Was marked Done but could not apply: required pg_partman, absent from the postgres:15-alpine image IDD 8.2 pins. Rewritten to use native PostgreSQL 15 declarative partitioning with create_monthly_partitions(). Verified by scripts/verify_migrations.sh (goose up, down-to 0, up again).
A12: DB-011 | B12: Week 2 | C12: Migration: cgnat_allocations (partitioned) | D12: FR-NET-001, FR-NET-002 | E12: DBD §6.2 cgnat_allocations | F12: DB-003 | G12: Qwen3-14B-Q4_K_M | H12: ~2,500 | I12: You are a Go 1.21 backend engineer. Project: ISP BSS/OSS. Stack: Go 1.21, PostgreSQL 15, Redis 7.2 Sentinel, Asynq. Rules: no global state | all errors wrapped with fmt.Errorf | all DB calls use context.Context | decimal.Decimal for ALL money | never log plaintext PII (aadhaar/pan/mobile) | structured JSON logs via zerolog. Package naming: internal/{module}, pkg/{shared}. FR being implemented: [PASTE ONE FR LINE FROM SRS §2.1] DDS reference: [PASTE RELEVANT SCAFFOLD FROM DDS] | J12: Generate a goose migration SQL file for the table below. PostgreSQL 15 syntax. Include +goose Up and +goose Down sections. In +goose Down, DROP TABLE CASCADE. Add ONLY the indexes listed — no extras. Use TIMESTAMPTZ not TIMESTAMP. Never use SERIAL for tables that will be partitioned — use BIGSERIAL. Table spec: [PASTE TABLE FROM DBD §6.2] Indexes: [PASTE INDEXES FOR THIS TABLE FROM DBD §6.4] Partitioned on allocated_at (monthly) via pg_partman. Create idx_cgnat_lea index with INCLUDE(subscriber_id,port_start,port_end,released_at). | K12: psql -c "SELECT tablename FROM pg_tables WHERE tablename LIKE 'cgnat_allocations%';" | L12: Parent + 3 monthly partitions | M12: psql -c "\d+ cgnat_allocations" | N12: Port range columns INTEGER | idx_cgnat_lea INCLUDE clause correct | O12: Model may use TIMESTAMP instead of TIMESTAMPTZ for allocated_at | P12: Done | Q12: db: add cgnat_allocations partitioned table migration | R12: Same pg_partman problem as DB-010; now uses create_monthly_partitions() from migration 010. 4 monthly partitions confirmed (current + 3 ahead), and a current-month insert routes correctly.
... A16: DB-015 | B16: Week 2 | C16: Run full goose migration + seed test data | D16: All DB FRs | E16: DXD §11.5 | F16: DB-001..DB-014 | G16: N/A | H16: N/A | I16: You are a Go 1.21 backend engineer. Project: ISP BSS/OSS. Stack: Go 1.21, PostgreSQL 15, Redis 7.2 Sentinel, Asynq. Rules: no global state | all errors wrapped with fmt.Errorf | all DB calls use context.Context | decimal.Decimal for ALL money | never log plaintext PII (aadhaar/pan/mobile) | structured JSON logs via zerolog. Package naming: internal/{module}, pkg/{shared}. FR being implemented: [PASTE ONE FR LINE FROM SRS §2.1] DDS reference: [PASTE RELEVANT SCAFFOLD FROM DDS] | J16: N/A — manual: goose -dir ./migrations postgres "$DSN" up psql -h localhost -U postgres -d isp_bss_oss -f scripts/seed_local.sql | K16: psql -c 'SELECT COUNT(*) FROM plans;' # expect ≥ 3 rows | L16: Migrations: all applied | Plans: 3 rows | GST rates: 1 row | M16: goose -dir ./migrations postgres "$DSN" status # all = Applied | N16: Zero failed migrations | seed data present | all FKs satisfied by seed data | O16: FK violations in seed data if insertion order is wrong — franchises before subscribers | P16: Done | Q16: db: all migrations applied and seed data loaded | R16: Full goose up / down-to 0 / up cycle now passes; previously blocked by the pg_partman migrations and by migration 003's trigger function lacking +goose StatementBegin/End, which goose split at the first internal semicolon. Run scripts/verify_migrations.sh.
A17: DB-016 | B17: Week 2 | C17: Migration: persistence-layer columns (fup_active, ledger account, KYC uniqueness) | D17: FR-FUP-001, FR-REV-002, FR-SEC-002 | E17: DBD 6.2 corrections | F17: DB-003, DB-005, DB-007 | G17: N/A | H17: N/A | J17: N/A - written while implementing internal/db against the interfaces the domain packages already declared. | K17: go test -tags=integration ./internal/db/... (TestFUPStore_SetFUPActive, TestRevenueStore_LedgerVariance, TestAPIStore_UpsertKYC) | L17: subscribers.fup_active added; wallet_ledgers.account added with CHECK; kyc_verifications gains uq_kyc_subscriber | M17: ./scripts/verify_migrations.sh && ./scripts/run_db_tests.sh | N17: goose up/down clean | FUP throttle state persists | ledger variance detects drift | KYC upsert does not duplicate | O17: Without account on wallet_ledgers the FR-REV-002 variance is zero by construction, since both recharge legs share a subscriber_id | P17: Done | Q17: db: add fup_active, wallet ledger account and KYC uniqueness | R17: Three columns the application code required that no earlier migration created. Each was found by implementing the persistence layer, not by review.

Sheet 🔐 Crypto Module
A1: Session ID | B1: Phase/Week | C1: Task Title | D1: FR IDs | E1: Doc Reference | F1: Prerequisites | G1: Model | H1: Est. Context Tokens | I1: System Block (paste first) | J1: LM Studio Prompt (paste verbatim) | K1: Test You Write First (before LM Studio) | L1: Expected Output | M1: Verification Command | N1: Quality Gates | O1: Risk Flags | P1: Status | Q1: Commit Message | R1: Notes
A2: CRY-001 | B2: Week 3 | C2: Define KeyStore interface + AESEncryptor struct | D2: FR-SEC-002, FR-SEC-003 | E2: DDS §5.5 | F2: ENV-006 | G2: Qwen3-14B-Q4_K_M | H2: ~3,500 | I2: You are a Go 1.21 backend engineer. Project: ISP BSS/OSS. Stack: Go 1.21, PostgreSQL 15, Redis 7.2 Sentinel, Asynq. Rules: no global state | all errors wrapped with fmt.Errorf | all DB calls use context.Context | decimal.Decimal for ALL money | never log plaintext PII (aadhaar/pan/mobile) | structured JSON logs via zerolog. Package naming: internal/{module}, pkg/{shared}. FR being implemented: [PASTE ONE FR LINE FROM SRS §2.1] DDS reference: [PASTE RELEVANT SCAFFOLD FROM DDS] | J2: System block + FR-SEC-002 + FR-SEC-003 + DDS §5.5 scaffold. Generate pkg/crypto/types.go containing: 1. KeyStore interface with GetKey(versionID string) ([]byte, error) 2. AESEncryptor struct with key []byte and keyVersion string fields 3. NewAESEncryptor(key []byte, version string) *AESEncryptor constructor Return ONLY the package declaration, imports, interface, struct, and constructor. No Encrypt or Decrypt methods yet. | K2: func TestNewAESEncryptor(t *testing.T) { enc := NewAESEncryptor(make([]byte, 32), "v1") assert.NotNil(t, enc) assert.Equal(t, "v1", enc.keyVersion) } | L2: Compiling pkg/crypto/types.go with correct struct fields | M2: go build ./pkg/crypto/ && go test -race ./pkg/crypto/ | N2: go vet clean | no exported fields on AESEncryptor (key must be private) | O2: Model may export key field — must be private (lowercase) | P2: Done | Q2: feat(crypto): CRY-001 AESEncryptor struct and KeyStore interface
A3: CRY-002 | B3: Week 3 | C3: Implement Encrypt method | D3: FR-SEC-002, FR-SEC-003 | E3: DDS §5.5 | F3: CRY-001 | G3: Qwen3-14B-Q4_K_M | H3: ~4,000 | I3: You are a Go 1.21 backend engineer. Project: ISP BSS/OSS. Stack: Go 1.21, PostgreSQL 15, Redis 7.2 Sentinel, Asynq. Rules: no global state | all errors wrapped with fmt.Errorf | all DB calls use context.Context | decimal.Decimal for ALL money | never log plaintext PII (aadhaar/pan/mobile) | structured JSON logs via zerolog. Package naming: internal/{module}, pkg/{shared}. FR being implemented: [PASTE ONE FR LINE FROM SRS §2.1] DDS reference: [PASTE RELEVANT SCAFFOLD FROM DDS] | J3: System block + DDS §5.5 Encrypt code pattern. Add method (e *AESEncryptor) Encrypt(plaintext string) (string, error) to pkg/crypto/encryptor.go. Format: "{keyVersion}:{base64(nonce+ciphertext)}" Use AES-GCM. Use io.ReadFull(rand.Reader,nonce). Return versioned ciphertext string. | K3: func TestEncrypt_ProducesVersionedCiphertext(t *testing.T) { key := make([]byte, 32) enc := NewAESEncryptor(key, "v1") ct, err := enc.Encrypt("123456789012") assert.NoError(t, err) assert.True(t, strings.HasPrefix(ct, "v1:")) assert.Greater(t, len(ct), 10) } | L3: Ciphertext starts with 'v1:' and is base64-encoded | M3: go test -race -v ./pkg/crypto/ -run TestEncrypt | N3: Output format is exactly {version}:{base64} | Two encryptions of same plaintext produce DIFFERENT ciphertexts (random nonce) | O3: Model may forget nonce randomness | may return base64 without version prefix | P3: Done | Q3: feat(crypto): CRY-002 Encrypt method with versioned ciphertext
A4: CRY-003 | B4: Week 3 | C4: Implement Decrypt function | D4: FR-SEC-003 | E4: DDS §5.5 | F4: CRY-002 | G4: Qwen3-14B-Q4_K_M | H4: ~4,000 | I4: You are a Go 1.21 backend engineer. Project: ISP BSS/OSS. Stack: Go 1.21, PostgreSQL 15, Redis 7.2 Sentinel, Asynq. Rules: no global state | all errors wrapped with fmt.Errorf | all DB calls use context.Context | decimal.Decimal for ALL money | never log plaintext PII (aadhaar/pan/mobile) | structured JSON logs via zerolog. Package naming: internal/{module}, pkg/{shared}. FR being implemented: [PASTE ONE FR LINE FROM SRS §2.1] DDS reference: [PASTE RELEVANT SCAFFOLD FROM DDS] | J4: System block + DDS §5.5 Decrypt code pattern. Add function Decrypt(versionedCiphertext string, keyStore KeyStore) (string, error) to pkg/crypto/encryptor.go. Must: split on first ':' to get version | call keyStore.GetKey(version) | base64 decode | AES-GCM decrypt. Return plaintext string or wrapped error. | K4: func TestDecrypt_RoundTrip(t *testing.T) { key := make([]byte, 32) enc := NewAESEncryptor(key, "v1") ct, _ := enc.Encrypt("987654321012") store := &mockKeyStore{"v1": key} plain, err := Decrypt(ct, store) assert.NoError(t, err) assert.Equal(t, "987654321012", plain) } | L4: Decrypted plaintext matches original input | M4: go test -race -v ./pkg/crypto/ -run TestDecrypt | N4: Tampered ciphertext returns error (not panic) | Wrong key version returns error | O4: Model may not handle the 'v1:' prefix split correctly | may panic on malformed input | P4: Done | Q4: feat(crypto): CRY-003 Decrypt with cross-version key store lookup
A5: CRY-004 | B5: Week 3 | C5: Cross-rotation decryption test | D5: FR-SEC-003 | E5: DDS §5.5, SecD §9.3 | F5: CRY-003 | G5: N/A — you write this test | H5: N/A | I5: You are a Go 1.21 backend engineer. Project: ISP BSS/OSS. Stack: Go 1.21, PostgreSQL 15, Redis 7.2 Sentinel, Asynq. Rules: no global state | all errors wrapped with fmt.Errorf | all DB calls use context.Context | decimal.Decimal for ALL money | never log plaintext PII (aadhaar/pan/mobile) | structured JSON logs via zerolog. Package naming: internal/{module}, pkg/{shared}. FR being implemented: [PASTE ONE FR LINE FROM SRS §2.1] DDS reference: [PASTE RELEVANT SCAFFOLD FROM DDS] | J5: N/A — manual test to write: func TestDecrypt_CrossKeyVersion(t *testing.T) { v1key := make([]byte, 32) v2key := bytes.Repeat([]byte{0x01}, 32) encV1 := NewAESEncryptor(v1key, "v1") ct, _ := encV1.Encrypt("sensitive_aadhaar") // Decrypt using store that has BOTH v1 and v2 keys store := &mockKeyStore{"v1": v1key, "v2": v2key} plain, err := Decrypt(ct, store) assert.NoError(t, err) assert.Equal(t, "sensitive_aadhaar", plain) } | K5: go test -race ./pkg/crypto/ -run TestDecrypt_CrossKeyVersion | L5: Test passes — v1 ciphertext decryptable even when v2 is the active key | M5: go test -race -v -count=3 ./pkg/crypto/ | N5: All 3 runs pass | race detector silent | O5: This is YOUR test — if it fails the Decrypt implementation is wrong, not the test | P5: Done | Q5: test(crypto): CRY-004 cross-rotation decryption verified

Sheet 📡 RADIUS AAA
A1: Session ID | B1: Phase/Week | C1: Task Title | D1: FR IDs | E1: Doc Reference | F1: Prerequisites | G1: Model | H1: Est. Context Tokens | I1: System Block (paste first) | J1: LM Studio Prompt (paste verbatim) | K1: Test You Write First (before LM Studio) | L1: Expected Output | M1: Verification Command | N1: Quality Gates | O1: Risk Flags | P1: Status | Q1: Commit Message | R1: Notes
A2: AAA-001 | B2: Week 4 | C2: RADIUS worker pool daemon struct + Start() | D2: FR-AAA-001 | E2: DDS §5.1, MDS §4.1 | F2: ENV-006, DB-003 | G2: Qwen3-14B-Q4_K_M | H2: ~5,000 | I2: You are a Go 1.21 backend engineer. Project: ISP BSS/OSS. Stack: Go 1.21, PostgreSQL 15, Redis 7.2 Sentinel, Asynq. Rules: no global state | all errors wrapped with fmt.Errorf | all DB calls use context.Context | decimal.Decimal for ALL money | never log plaintext PII (aadhaar/pan/mobile) | structured JSON logs via zerolog. Package naming: internal/{module}, pkg/{shared}. FR being implemented: [PASTE ONE FR LINE FROM SRS §2.1] DDS reference: [PASTE RELEVANT SCAFFOLD FROM DDS] | J2: System block + FR-AAA-001 + DDS §5.1 Start() scaffold. Generate internal/radius/daemon.go with: 1. RadiusDaemon struct: addr string, secret []byte, packetQueue chan *radius.Request, pools (Redis+PG) 2. NewRadiusDaemon constructor 3. Start() method: ListenUDP :1812, spawn 128 goroutines calling workerPoolConsumer(), start radius.PacketServer 4. Empty workerPoolConsumer() stub Return ONLY daemon.go. No handler logic yet. | K2: func TestRadiusDaemon_StartStops(t *testing.T) { d := NewRadiusDaemon(":19812", []byte("secret"), nil) ctx, cancel := context.WithTimeout(context.Background(), 100*time.Millisecond) defer cancel() err := d.StartWithContext(ctx) assert.NoError(t, err) } | L2: Daemon struct compiles | goroutines spawned without panic | M2: go build ./internal/radius/ && go test -race ./internal/radius/ -run TestRadiusDaemon_StartStops | N2: 128 workers confirmed via goroutine count | no goroutine leak after context cancel | O2: layeh.com/radius API — PacketServer.Serve signature may differ | model may use wrong import path | P2: Done | Q2: feat(radius): AAA-001 worker pool daemon with bounded 128-worker channel
A3: AAA-002 | B3: Week 4 | C3: RADIUS Auth handler — Redis cache lookup | D3: FR-AAA-002 | E3: DDS §5.1, MDS §4.1 | F3: AAA-001 | G3: Qwen3-14B-Q4_K_M | H3: ~5,500 | I3: You are a Go 1.21 backend engineer. Project: ISP BSS/OSS. Stack: Go 1.21, PostgreSQL 15, Redis 7.2 Sentinel, Asynq. Rules: no global state | all errors wrapped with fmt.Errorf | all DB calls use context.Context | decimal.Decimal for ALL money | never log plaintext PII (aadhaar/pan/mobile) | structured JSON logs via zerolog. Package naming: internal/{module}, pkg/{shared}. FR being implemented: [PASTE ONE FR LINE FROM SRS §2.1] DDS reference: [PASTE RELEVANT SCAFFOLD FROM DDS] | J3: System block + FR-AAA-002 + DDS §5.1 auth flow. Generate internal/radius/handlers.go handleAuth() function: 1. Extract username from RADIUS packet 2. Redis HGET subscriber:{username} — check status field 3. If status=='active': build RADIUS Accept; record latency metric; return 4. If MISS: PostgreSQL fallback; re-cache result with TTL; return 5. If status!='active': RADIUS Reject; return Must emit radiusAuthDuration.Observe() and radiusAuthTotal.Inc() metrics. | K3: func TestHandleAuth_ActiveSubscriberAccepted(t *testing.T) { // seed Redis with active subscriber rdb.HSet(ctx, "subscriber:testuser", "status","active","plan_id","1") // fire test RADIUS Access-Request result := fireTestAuth("testuser", "secret") assert.Equal(t, radius.CodeAccessAccept, result.Code) } | L3: Access-Accept returned for active subscriber | M3: go test -race -tags=integration ./internal/radius/ -run TestHandleAuth | N3: Latency metric emitted | Cache populated after DB fallback | Suspended subscriber gets Access-Reject | O3: Redis HGET returns empty string on miss — model may treat empty string as active | P3: Done | Q3: feat(radius): AAA-002 auth handler with Redis cache and PG fallback
A4: AAA-003 | B4: Week 4 | C4: Accounting deduplication — SetNX pattern | D4: FR-AAA-003 | E4: DDS §5.2 | F4: AAA-002 | G4: Qwen3-14B-Q4_K_M | H4: ~4,000 | I4: You are a Go 1.21 backend engineer. Project: ISP BSS/OSS. Stack: Go 1.21, PostgreSQL 15, Redis 7.2 Sentinel, Asynq. Rules: no global state | all errors wrapped with fmt.Errorf | all DB calls use context.Context | decimal.Decimal for ALL money | never log plaintext PII (aadhaar/pan/mobile) | structured JSON logs via zerolog. Package naming: internal/{module}, pkg/{shared}. FR being implemented: [PASTE ONE FR LINE FROM SRS §2.1] DDS reference: [PASTE RELEVANT SCAFFOLD FROM DDS] | J4: System block + FR-AAA-003 + DDS §5.2 dedup code pattern. Add handleAccounting() to internal/radius/handlers.go. For Interim-Update packets ONLY: dedupKey := 'acct_dedup:' + sessionID + ':' + strconv.FormatUint(inputOctets, 10) isNew, err := rdb.SetNX(ctx, dedupKey, '1', 30*time.Second).Result() if !isNew → ACK and return; radiusDedupSkipped.Inc() For all packets: HINCRBY usage:{sessionID} input_bytes / output_bytes | K4: func TestDedup_DuplicateInterimSkipped(t *testing.T) { // send same Interim-Update packet twice first := fireTestAccounting(sessionID, inputOctets) second := fireTestAccounting(sessionID, inputOctets) // only first should increment Redis counter count := rdb.HGet(ctx, 'usage:'+sessionID, 'input_bytes').Val() assert.Equal(t, strconv.Itoa(inputOctets), count) } | L4: Redis counter incremented only once for duplicate packets | M4: go test -race -tags=integration ./internal/radius/ -run TestDedup -count=3 | N4: Race detector silent | Counter NOT double-incremented | HINCRBY not HSET used | O4: Model may use GET + SET instead of SetNX — this is NOT atomic; reject it | P4: Done | Q4: feat(radius): AAA-003 accounting deduplication via atomic SetNX
A5: AAA-004 | B5: Week 4 | C5: Brute-force rate limiter (FR-SEC-001) | D5: FR-SEC-001 | E5: MDS §4.1 | F5: AAA-002 | G5: Qwen3-14B-Q4_K_M | H5: ~4,500 | I5: You are a Go 1.21 backend engineer. Project: ISP BSS/OSS. Stack: Go 1.21, PostgreSQL 15, Redis 7.2 Sentinel, Asynq. Rules: no global state | all errors wrapped with fmt.Errorf | all DB calls use context.Context | decimal.Decimal for ALL money | never log plaintext PII (aadhaar/pan/mobile) | structured JSON logs via zerolog. Package naming: internal/{module}, pkg/{shared}. FR being implemented: [PASTE ONE FR LINE FROM SRS §2.1] DDS reference: [PASTE RELEVANT SCAFFOLD FROM DDS] | J5: System block + FR-SEC-001. Add brute-force check to handleAuth() in handlers.go: key := 'auth_fail:' + username count, _ := rdb.Incr(ctx, key).Result() if count == 1 { rdb.Expire(ctx, key, 60*time.Second) } if count > 10 { rdb.Set(ctx, 'auth_ban:'+username, '1', 15*time.Minute) return radius.CodeAccessReject } Check ban key BEFORE any DB/cache lookup — banned users must be rejected immediately. | K5: func TestBruteForce_BlocksAt10Failures(t *testing.T) { for i := 0; i < 10; i++ { fireTestAuth('baduser', 'wrongpwd') } result := fireTestAuth('baduser', 'correctpwd') assert.Equal(t, radius.CodeAccessReject, result.Code) } | L5: 11th attempt rejected even with correct password | M5: go test -race -tags=integration ./internal/radius/ -run TestBruteForce | N5: Ban expires after 15 minutes (verify TTL in Redis) | Counter expires after 60s | O5: Model may check ban after cache lookup — must check ban FIRST | P5: Done | Q5: feat(radius): AAA-004 brute-force rate limiter with 15-min ban
A6: AAA-005 | B6: Week 5 | C6: NFR-PERF-001 load test — radperf ≤15ms p99 | D6: NFR-PERF-001 | E6: TST §13.4 | F6: AAA-001..AAA-004 | G6: N/A — performance test | H6: N/A | I6: You are a Go 1.21 backend engineer. Project: ISP BSS/OSS. Stack: Go 1.21, PostgreSQL 15, Redis 7.2 Sentinel, Asynq. Rules: no global state | all errors wrapped with fmt.Errorf | all DB calls use context.Context | decimal.Decimal for ALL money | never log plaintext PII (aadhaar/pan/mobile) | structured JSON logs via zerolog. Package naming: internal/{module}, pkg/{shared}. FR being implemented: [PASTE ONE FR LINE FROM SRS §2.1] DDS reference: [PASTE RELEVANT SCAFFOLD FROM DDS] | J6: N/A — run load test: 1. Pre-seed Redis with 5,000 active subscriber sessions 2. go run cmd/radiusd/main.go & 3. radperf --server localhost:1812 --secret my_secret --rate 1000 --duration 60 --users ./scripts/test_users.txt 4. Check p99 in output | K6: radperf output: p99_latency_ms < 15 | L6: p99 ≤ 15ms | error rate < 0.01% | M6: radperf output shows p99 latency | check prometheus metric: histogram_quantile(0.99, radius_auth_duration_seconds) | N6: p99 ≤ 15ms | No worker pool starvation (radius_worker_queue_depth stays < 50) | Race detector clean | O6: 12GB GPU inference running simultaneously may cause CPU contention — stop LM Studio before load test | P6: Done | Q6: test(radius): AAA-005 NFR-PERF-001 verified ≤15ms p99

Sheet 💳 Billing Module
A1: Session ID | B1: Phase/Week | C1: Task Title | D1: FR IDs | E1: Doc Reference | F1: Prerequisites | G1: Model | H1: Est. Context Tokens | I1: System Block (paste first) | J1: LM Studio Prompt (paste verbatim) | K1: Test You Write First (before LM Studio) | L1: Expected Output | M1: Verification Command | N1: Quality Gates | O1: Risk Flags | P1: Status | Q1: Commit Message | R1: Notes
A2: BIL-001 | B2: Week 6 | C2: GST calculation — CalculateGstInvoice() | D2: FR-BIL-001, FR-BIL-002 | E2: DDS §5.4, MDS §4.3 | F2: DB-006, ENV-006 | G2: Qwen3-14B-Q4_K_M | H2: ~4,500 | I2: You are a Go 1.21 backend engineer. Project: ISP BSS/OSS. Stack: Go 1.21, PostgreSQL 15, Redis 7.2 Sentinel, Asynq. Rules: no global state | all errors wrapped with fmt.Errorf | all DB calls use context.Context | decimal.Decimal for ALL money | never log plaintext PII (aadhaar/pan/mobile) | structured JSON logs via zerolog. Package naming: internal/{module}, pkg/{shared}. FR being implemented: [PASTE ONE FR LINE FROM SRS §2.1] DDS reference: [PASTE RELEVANT SCAFFOLD FROM DDS] | J2: System block + FR-BIL-001 + FR-BIL-002 + DDS §5.4 code pattern. Generate internal/billing/gst.go with CalculateGstInvoice(baseAmount decimal.Decimal, state string, rate db.GstRate) db.Invoice. RULE: Never use float64. Use decimal.Decimal.Mul().Div(100).Round(2). State 'TN' → CGST+SGST, igst=0. Else → IGST only, cgst=sgst=0. | K2: func TestCalculateGstInvoice_TN(t *testing.T) { base := decimal.NewFromFloat(799.00) rate := db.GstRate{CgstRate:decimal.NewFromFloat(9),SgstRate:decimal.NewFromFloat(9),IgstRate:decimal.NewFromFloat(18)} inv := CalculateGstInvoice(base, "TN", rate) assert.Equal(t, "71.91", inv.CgstAmount.String()) assert.Equal(t, "71.91", inv.SgstAmount.String()) assert.True(t, inv.IgstAmount.IsZero()) assert.Equal(t, "942.82", inv.TotalAmount.String()) } | L2: 71.91 CGST, 71.91 SGST, 0 IGST, 942.82 total | M2: go test -race ./internal/billing/ -run TestCalculateGstInvoice && grep -n 'float' internal/billing/gst.go # zero hits required | N2: grep -n 'float64' returns zero hits | Interstate test also passes (18% IGST only) | O2: Model will use float64 unless explicitly prohibited every session — check grep output | P2: Done | Q2: feat(billing): BIL-001 GST calculation with decimal.Decimal
A3: BIL-002 | B3: Week 6 | C3: Wallet recharge — double-entry + idempotency | D3: FR-BIL-003, FR-BIL-005 | E3: DDS §5.6, MDS §4.3 | F3: DB-007, BIL-001 | G3: Qwen3-14B-Q4_K_M | H3: ~5,500 | I3: You are a Go 1.21 backend engineer. Project: ISP BSS/OSS. Stack: Go 1.21, PostgreSQL 15, Redis 7.2 Sentinel, Asynq. Rules: no global state | all errors wrapped with fmt.Errorf | all DB calls use context.Context | decimal.Decimal for ALL money | never log plaintext PII (aadhaar/pan/mobile) | structured JSON logs via zerolog. Package naming: internal/{module}, pkg/{shared}. FR being implemented: [PASTE ONE FR LINE FROM SRS §2.1] DDS reference: [PASTE RELEVANT SCAFFOLD FROM DDS] | J3: System block + FR-BIL-003 + FR-BIL-005 + DDS §5.6 wallet pattern. Generate internal/billing/wallet.go with WalletService.Recharge(ctx, RechargeRequest) (*Transaction, error). MUST: 1) Check transaction_token idempotency first (return existing if found) 2) Run double-entry in Serializable transaction: debit entry + credit entry + UPDATE subscribers.wallet_balance 3) Return created transaction. | K3: func TestWalletRecharge_Idempotent(t *testing.T) { req := RechargeRequest{SubscriberID:1, Amount:decimal.NewFromFloat(799), Token:"tok_abc"} tx1, _ := svc.Recharge(ctx, req) tx2, _ := svc.Recharge(ctx, req) // same token assert.Equal(t, tx1.ID, tx2.ID) // same transaction returned bal := getBalance(1) assert.Equal(t, "799.00", bal.String()) // credited only once } | L3: Second call returns same transaction ID | Balance incremented only once | M3: go test -race -tags=integration ./internal/billing/ -run TestWalletRecharge | N3: Serializable isolation used | Balance updated atomically with ledger entries | Idempotency works across restarts | O3: Model may use READ COMMITTED instead of Serializable | May forget to UPDATE wallet_balance | P3: Done | Q3: feat(billing): BIL-002 wallet double-entry recharge with idempotency
A4: BIL-003 | B4: Week 6 | C4: Razorpay webhook HMAC validation | D4: FR-SEC-004 | E4: DDS §5.6 | F4: BIL-002 | G4: Qwen3-14B-Q4_K_M | H4: ~3,500 | I4: You are a Go 1.21 backend engineer. Project: ISP BSS/OSS. Stack: Go 1.21, PostgreSQL 15, Redis 7.2 Sentinel, Asynq. Rules: no global state | all errors wrapped with fmt.Errorf | all DB calls use context.Context | decimal.Decimal for ALL money | never log plaintext PII (aadhaar/pan/mobile) | structured JSON logs via zerolog. Package naming: internal/{module}, pkg/{shared}. FR being implemented: [PASTE ONE FR LINE FROM SRS §2.1] DDS reference: [PASTE RELEVANT SCAFFOLD FROM DDS] | J4: System block + FR-SEC-004 + DDS §5.6 HMAC code. Generate internal/billing/webhook.go with ValidateRazorpaySignature(payload []byte, razorpaySignature, webhookSecret string) error. IMPORTANT: payload is raw []byte BEFORE json.Unmarshal. HMAC-SHA256 of payload vs header. | K4: func TestWebhookHMAC_InvalidSignatureRejected(t *testing.T) { payload := []byte(`{"event":"payment.captured"}`) err := ValidateRazorpaySignature(payload, "invalid_sig", "test_secret") assert.Error(t, err) } func TestWebhookHMAC_ValidSignatureAccepted(t *testing.T) { payload := []byte(`{"event":"payment.captured"}`) mac := hmac.New(sha256.New, []byte("test_secret")) mac.Write(payload) sig := hex.EncodeToString(mac.Sum(nil)) err := ValidateRazorpaySignature(payload, sig, "test_secret") assert.NoError(t, err) } | L4: Invalid sig returns error | Valid sig returns nil | M4: go test -race ./internal/billing/ -run TestWebhookHMAC | N4: hmac.Equal used (not == for timing safety) | webhookHMACFailures metric incremented on failure | O4: Model may use == for comparison instead of hmac.Equal — timing attack vulnerability | P4: Done | Q4: feat(billing): BIL-003 Razorpay webhook HMAC validation
A5: BIL-004 | B5: Week 6 | C5: Dunning state machine — stage transitions | D5: FR-BIL-004 | E5: MDS §4.3 dunning state machine | F5: BIL-002 | G5: Qwen3-14B-Q4_K_M | H5: ~5,000 | I5: You are a Go 1.21 backend engineer. Project: ISP BSS/OSS. Stack: Go 1.21, PostgreSQL 15, Redis 7.2 Sentinel, Asynq. Rules: no global state | all errors wrapped with fmt.Errorf | all DB calls use context.Context | decimal.Decimal for ALL money | never log plaintext PII (aadhaar/pan/mobile) | structured JSON logs via zerolog. Package naming: internal/{module}, pkg/{shared}. FR being implemented: [PASTE ONE FR LINE FROM SRS §2.1] DDS reference: [PASTE RELEVANT SCAFFOLD FROM DDS] | J5: System block + FR-BIL-004 + MDS §4.3 dunning state machine diagram. Generate internal/billing/dunning.go with DunningEngine.EvaluateSubscriber(ctx, sub db.Subscriber) ([]asynq.Task, error). Logic: check plan_expiry against now. Return list of Asynq tasks to enqueue based on current dunning_state and elapsed time. States: active→reminded_7d→reminded_3d→reminded_1d→grace_period→soft_suspended→hard_suspended. | K5: func TestDunning_T7DReminder(t *testing.T) { sub := db.Subscriber{PlanExpiry: time.Now().Add(7*24*time.Hour), DunningState:"active"} tasks, err := engine.EvaluateSubscriber(ctx, sub) assert.NoError(t, err) assert.Len(t, tasks, 1) assert.Equal(t, "dunning:remind", tasks[0].Type()) } | L5: T-7d triggers dunning:remind task | M5: go test -race ./internal/billing/ -run TestDunning | N5: All state transitions tested | T+24h triggers CoA throttle task | T+72h triggers PoD task | O5: Model may use time.Now() directly — must use injected clock for testability | P5: Done | Q5: feat(billing): BIL-004 dunning engine state machine
A6: BIL-005 | B6: Week 7 | C6: GSTR-1 export builder | D6: FR-BIL-006 | E6: MDS §4.3 GSTR-1 export | F6: DB-006, BIL-001 | G6: Qwen3-14B-Q4_K_M | H6: ~5,000 | I6: You are a Go 1.21 backend engineer. Project: ISP BSS/OSS. Stack: Go 1.21, PostgreSQL 15, Redis 7.2 Sentinel, Asynq. Rules: no global state | all errors wrapped with fmt.Errorf | all DB calls use context.Context | decimal.Decimal for ALL money | never log plaintext PII (aadhaar/pan/mobile) | structured JSON logs via zerolog. Package naming: internal/{module}, pkg/{shared}. FR being implemented: [PASTE ONE FR LINE FROM SRS §2.1] DDS reference: [PASTE RELEVANT SCAFFOLD FROM DDS] | J6: System block + FR-BIL-006. Generate internal/billing/gstr1.go with BuildGSTR1Export(ctx, month time.Time) (*GSTR1Report, error). Report must contain: B2BInvoices []B2BEntry (subscriber with GSTIN), B2CSummary map[string]B2CSummaryEntry (state→aggregate), HSNSummary []HSNEntry. Query invoices table grouped by registered_state and entry type. | K6: func TestGSTR1_B2CSummaryByState(t *testing.T) { // seed 3 TN invoices, 2 KA invoices report, err := BuildGSTR1Export(ctx, testMonth) assert.NoError(t, err) assert.Equal(t, 2, len(report.B2CSummary)) // TN and KA assert.Equal(t, 3, report.B2CSummary["TN"].InvoiceCount) } | L6: Correct state-wise invoice aggregation | M6: go test -race -tags=integration ./internal/billing/ -run TestGSTR1 | N6: No float64 in any amount fields | HSN code populated from plan config | O6: Model may hardcode HSN code — must come from plan configuration | P6: Done | Q6: feat(billing): BIL-005 GSTR-1 export builder
A7: BIL-006 | B7: Week 7 | C7: Invoice PDF with usage summary via Gotenberg | D7: FR-BIL-007 | E7: MDS §4.3, IDD §8.2 | F7: ENV-007, DB-006 | G7: Qwen3-14B-Q4_K_M | H7: ~4,500 | I7: You are a Go 1.21 backend engineer. Project: ISP BSS/OSS. Stack: Go 1.21, PostgreSQL 15, Redis 7.2 Sentinel, Asynq. Rules: no global state | all errors wrapped with fmt.Errorf | all DB calls use context.Context | decimal.Decimal for ALL money | never log plaintext PII (aadhaar/pan/mobile) | structured JSON logs via zerolog. Package naming: internal/{module}, pkg/{shared}. FR being implemented: [PASTE ONE FR LINE FROM SRS §2.1] DDS reference: [PASTE RELEVANT SCAFFOLD FROM DDS] | J7: System block + FR-BIL-007. Generate internal/billing/pdf.go with GenerateInvoicePDF(ctx, inv db.Invoice) ([]byte, error). Build HTML template string with invoice fields. POST to http://gotenberg_engine:3000/forms/chromium/convert/html. Include plain-language usage block: 'Data used this cycle: {gb_used} GB of {gb_included} GB included'. Return PDF bytes. | K7: func TestInvoicePDF_ContainsUsageSummary(t *testing.T) { inv := db.Invoice{GbUsed:2847.0, GbIncluded:3300} pdfBytes, err := GenerateInvoicePDF(ctx, inv) assert.NoError(t, err) assert.Greater(t, len(pdfBytes), 1000) // non-empty PDF } | L7: PDF bytes returned | Size > 1KB | M7: go test -race -tags=integration ./internal/billing/ -run TestInvoicePDF | N7: PDF opens in viewer | Usage summary text present | GST amounts correct | O7: Gotenberg URL must use container name in Docker network, not localhost | P7: Done | Q7: feat(billing): BIL-006 invoice PDF with usage summary via Gotenberg

Sheet 🔔 Notifications
A1: Session ID | B1: Phase/Week | C1: Task Title | D1: FR IDs | E1: Doc Reference | F1: Prerequisites | G1: Model | H1: Est. Context Tokens | I1: System Block (paste first) | J1: LM Studio Prompt (paste verbatim) | K1: Test You Write First (before LM Studio) | L1: Expected Output | M1: Verification Command | N1: Quality Gates | O1: Risk Flags | P1: Status | Q1: Commit Message | R1: Notes
A2: NOT-001 | B2: Week 8 | C2: DND check + notification dispatcher base | D2: FR-NOTIF-008, FR-NOTIF-009 | E2: MDS §4.7 DND check flow, DDS §5.8 | F2: DB-008 | G2: Qwen3-14B-Q4_K_M | H2: ~5,000 | I2: You are a Go 1.21 backend engineer. Project: ISP BSS/OSS. Stack: Go 1.21, PostgreSQL 15, Redis 7.2 Sentinel, Asynq. Rules: no global state | all errors wrapped with fmt.Errorf | all DB calls use context.Context | decimal.Decimal for ALL money | never log plaintext PII (aadhaar/pan/mobile) | structured JSON logs via zerolog. Package naming: internal/{module}, pkg/{shared}. FR being implemented: [PASTE ONE FR LINE FROM SRS §2.1] DDS reference: [PASTE RELEVANT SCAFFOLD FROM DDS] | J2: System block + FR-NOTIF-008 + FR-NOTIF-009 + MDS §4.7 DND flow. Generate internal/notifications/dispatcher.go with Dispatcher.Dispatch(ctx, NotificationTask) error. Must: 1) Load subscriber.dnd_opt_out from DB 2) If opted out AND task.Class=="marketing": write notification_log with status='suppressed_dnd' and return nil 3) If allowed: proceed (stub actual send for now) 4) Always write notification_log record on every attempt. | K2: func TestDispatcher_DND_SuppressesMarketing(t *testing.T) { sub := seedSubscriber(t, dndOptOut: true) task := NotificationTask{SubscriberID:sub.ID, Class:"marketing", TemplateID:"TMPL-003"} err := dispatcher.Dispatch(ctx, task) assert.NoError(t, err) // not an error — intentional skip logs := getNotifLogs(sub.ID) assert.Equal(t, "suppressed_dnd", logs[0].DeliveryStatus) } | L2: No message sent | notification_log row with suppressed_dnd | M2: go test -race -tags=integration ./internal/notifications/ -run TestDispatcher_DND | N2: notification_log record created even for suppressed messages | DND check happens BEFORE any API call | O2: Model may skip logging for suppressed messages — must log every attempt | P2: Done | Q2: feat(notifications): NOT-001 DND check and notification_log base
A3: NOT-002 | B3: Week 8 | C3: WhatsApp Business API template sender | D3: FR-NOTIF-010, FR-NOTIF-001..007 | E3: DDS §5.8 WhatsAppClient | F3: NOT-001 | G3: Qwen3-14B-Q4_K_M | H3: ~5,500 | I3: You are a Go 1.21 backend engineer. Project: ISP BSS/OSS. Stack: Go 1.21, PostgreSQL 15, Redis 7.2 Sentinel, Asynq. Rules: no global state | all errors wrapped with fmt.Errorf | all DB calls use context.Context | decimal.Decimal for ALL money | never log plaintext PII (aadhaar/pan/mobile) | structured JSON logs via zerolog. Package naming: internal/{module}, pkg/{shared}. FR being implemented: [PASTE ONE FR LINE FROM SRS §2.1] DDS reference: [PASTE RELEVANT SCAFFOLD FROM DDS] | J3: System block + DDS §5.8 WhatsAppClient code. Generate internal/notifications/whatsapp.go with WhatsAppClient.SendTemplate(ctx, TemplateMessage) error. Must: 1) POST to Meta Graph API https://graph.facebook.com/v17.0/{phoneNumberID}/messages 2) Authorization: Bearer {accessToken} 3) Build template payload with components from req.Variables 4) Parse response for message ID 5) Write notification_log with provider_message_id and status='sent'. | K3: func TestWhatsApp_SendTemplate_LogsProviderID(t *testing.T) { // mock HTTP server returning {messages:[{id:'wamid.test123'}]} client := NewWhatsAppClient(mockServer.URL, "test_phone_id", "test_token", db) msg := TemplateMessage{ToPhoneE164:"+919876543210", TemplateName:"fup_warning", TemplateID:"TMPL-001", SubscriberID:1} err := client.SendTemplate(ctx, msg) assert.NoError(t, err) log := getLatestNotifLog(1) assert.Equal(t, "wamid.test123", log.ProviderMessageID) } | L3: notification_log.provider_message_id = 'wamid.test123' | M3: go test -race ./internal/notifications/ -run TestWhatsApp | N3: Authorization header set correctly | Template variables built as components array | HTTP error returns wrapped error for Asynq retry | O3: Meta API returns 200 even for some errors — check messages array not just HTTP status | P3: Done | Q3: feat(notifications): NOT-002 WhatsApp Business API template sender
A4: NOT-003 | B4: Week 8 | C4: WhatsApp delivery status webhook handler | D4: FR-NOTIF-011 | E4: DDS §5.8 WhatsAppWebhook | F4: NOT-002 | G4: Qwen3-14B-Q4_K_M | H4: ~4,500 | I4: You are a Go 1.21 backend engineer. Project: ISP BSS/OSS. Stack: Go 1.21, PostgreSQL 15, Redis 7.2 Sentinel, Asynq. Rules: no global state | all errors wrapped with fmt.Errorf | all DB calls use context.Context | decimal.Decimal for ALL money | never log plaintext PII (aadhaar/pan/mobile) | structured JSON logs via zerolog. Package naming: internal/{module}, pkg/{shared}. FR being implemented: [PASTE ONE FR LINE FROM SRS §2.1] DDS reference: [PASTE RELEVANT SCAFFOLD FROM DDS] | J4: System block + FR-NOTIF-011 + DDS §5.8 webhook handler. Generate internal/notifications/webhook.go with WhatsAppWebhookHandler(w http.ResponseWriter, r *http.Request). Must: 1) GET handler: verify hub.verify_token from env, echo hub.challenge 2) POST handler: verify X-Hub-Signature-256 HMAC 3) Parse statuses array 4) For each status: UPDATE notification_log SET delivery_status WHERE provider_message_id = status.ID 5) Increment whatsappDeliveryStatusTotal metric. | K4: func TestWhatsAppWebhook_UpdatesDeliveryStatus(t *testing.T) { // seed notification_log with provider_message_id='wamid.abc' seedNotifLog(t, "wamid.abc", "sent") // POST valid webhook payload payload := buildDeliveryWebhook("wamid.abc", "delivered") postWebhook(t, handler, payload) log := getNotifLogByProviderID("wamid.abc") assert.Equal(t, "delivered", log.DeliveryStatus) } | L4: notification_log.delivery_status updated to 'delivered' | M4: go test -race -tags=integration ./internal/notifications/ -run TestWhatsAppWebhook | N4: HMAC verification rejects invalid signatures (returns 400) | GET verification challenge works | idx_notif_provider_id used for update query (check EXPLAIN) | O4: Meta sends nested JSON structure — model may parse wrong level of statuses array | P4: Done | Q4: feat(notifications): NOT-003 WhatsApp delivery status webhook
A5: NOT-004 | B5: Week 8 | C5: SMS gateway sender (MSG91/Twilio) | D5: FR-NOTIF-001..007 | E5: MDS §4.7 | F5: NOT-001 | G5: Qwen3-14B-Q4_K_M | H5: ~4,000 | I5: You are a Go 1.21 backend engineer. Project: ISP BSS/OSS. Stack: Go 1.21, PostgreSQL 15, Redis 7.2 Sentinel, Asynq. Rules: no global state | all errors wrapped with fmt.Errorf | all DB calls use context.Context | decimal.Decimal for ALL money | never log plaintext PII (aadhaar/pan/mobile) | structured JSON logs via zerolog. Package naming: internal/{module}, pkg/{shared}. FR being implemented: [PASTE ONE FR LINE FROM SRS §2.1] DDS reference: [PASTE RELEVANT SCAFFOLD FROM DDS] | J5: System block. Generate internal/notifications/sms.go with SMSClient.Send(ctx, to string, message string, templateID string) error. Support provider switching via SMS_GATEWAY_PROVIDER env var ('msg91' or 'twilio'). Write notification_log record on send. Return non-nil error on HTTP failure for Asynq retry. | K5: func TestSMSSend_LogsOnSuccess(t *testing.T) { // mock SMS provider HTTP server client := NewSMSClient(mockServer.URL, "test_key", "BSSOSS", db) err := client.Send(ctx, "+919876543210", "Test message", "TMPL-003") assert.NoError(t, err) logs := getNotifLogs(1) assert.Equal(t, "sms", logs[0].Channel) } | L5: notification_log with channel='sms' created | M5: go test -race ./internal/notifications/ -run TestSMSSend | N5: DLT sender ID included in MSG91 payload | Phone number in E.164 format validated before send | O5: Indian SMS requires DLT registration — model may forget sender ID header | P5: Done | Q5: feat(notifications): NOT-004 SMS gateway sender with provider switching
A6: NOT-005 | B6: Week 8 | C6: FUP 80% warning Asynq task handler | D6: FR-FUP-004, FR-NOTIF-002 | E6: MDS §4.7 TMPL-001 | F6: NOT-002, NOT-004 | G6: Qwen3-14B-Q4_K_M | H6: ~4,500 | I6: You are a Go 1.21 backend engineer. Project: ISP BSS/OSS. Stack: Go 1.21, PostgreSQL 15, Redis 7.2 Sentinel, Asynq. Rules: no global state | all errors wrapped with fmt.Errorf | all DB calls use context.Context | decimal.Decimal for ALL money | never log plaintext PII (aadhaar/pan/mobile) | structured JSON logs via zerolog. Package naming: internal/{module}, pkg/{shared}. FR being implemented: [PASTE ONE FR LINE FROM SRS §2.1] DDS reference: [PASTE RELEVANT SCAFFOLD FROM DDS] | J6: System block + FR-FUP-004 + MDS §4.2 task table (notif:fup_warning). Generate internal/tasks/fup_warning_task.go with HandleFUPWarningTask(ctx, task *asynq.Task) error. Unmarshal payload: {subscriber_id, gb_used, gb_total, plan_name}. Dispatch WhatsApp TMPL-001 + SMS via Dispatcher.Dispatch(). Max retries: 3. Return non-nil error on dispatch failure. | K6: func TestFUPWarningTask_DispatchesWhatsApp(t *testing.T) { payload, _ := json.Marshal(FUPWarningPayload{SubscriberID:1, GbUsed:2640, GbTotal:3300}) task := asynq.NewTask("notif:fup_warning", payload) err := HandleFUPWarningTask(ctx, task) assert.NoError(t, err) logs := getNotifLogsForSubscriber(1) assert.True(t, len(logs) >= 1) assert.Equal(t, "TMPL-001", logs[0].TemplateID) } | L6: WhatsApp dispatch called with TMPL-001 | notification_log created | M6: go test -race -tags=integration ./internal/tasks/ -run TestFUPWarningTask | N6: 80% threshold = gb_used/gb_total >= 0.8 | DND check triggered before dispatch | O6: Model may hardcode 80% — must use subscriber plan threshold from DB | P6: Done | Q6: feat(tasks): NOT-005 FUP 80% warning Asynq task handler

Sheet ⚡ FUP + Asynq
A1: Session ID | B1: Phase/Week | C1: Task Title | D1: FR IDs | E1: Doc Reference | F1: Prerequisites | G1: Model | H1: Est. Context Tokens | I1: System Block (paste first) | J1: LM Studio Prompt (paste verbatim) | K1: Test You Write First (before LM Studio) | L1: Expected Output | M1: Verification Command | N1: Quality Gates | O1: Risk Flags | P1: Status | Q1: Commit Message | R1: Notes
A2: FUP-001 | B2: Week 9 | C2: FUP scanner goroutine — 10s polling loop | D2: FR-FUP-001 | E2: MDS §4.2 | F2: AAA-003 | G2: Qwen3-14B-Q4_K_M | H2: ~5,000 | I2: You are a Go 1.21 backend engineer. Project: ISP BSS/OSS. Stack: Go 1.21, PostgreSQL 15, Redis 7.2 Sentinel, Asynq. Rules: no global state | all errors wrapped with fmt.Errorf | all DB calls use context.Context | decimal.Decimal for ALL money | never log plaintext PII (aadhaar/pan/mobile) | structured JSON logs via zerolog. Package naming: internal/{module}, pkg/{shared}. FR being implemented: [PASTE ONE FR LINE FROM SRS §2.1] DDS reference: [PASTE RELEVANT SCAFFOLD FROM DDS] | J2: System block + FR-FUP-001 + MDS §4.2 FUP threshold events table. Generate internal/fup/scanner.go with FUPScanner.Start(ctx context.Context). Every 10s: SCAN Redis for 'usage:*' keys. For each key: HGETALL → compare input_bytes+output_bytes vs plan threshold. If 80%+: enqueue notif:fup_warning with idempotency key 'fup_warn:{session}:{day}'. If 100%+: enqueue coa:send + notif:fup_throttle. | K2: func TestFUPScanner_EnqueuesCoAOn100Pct(t *testing.T) { // seed Redis: usage:sess1 = 3543348019200 bytes (100% of 3.3TB plan) rdb.HSet(ctx, "usage:sess1", "input_bytes","3543348019200","plan_threshold","3543348019200","session_id","sess1") scanner.runOnce(ctx) // check Asynq queue tasks, _ := inspector.ListActiveTasks("network_commands") assert.Equal(t, 1, len(tasks)) assert.Equal(t, "coa:send", tasks[0].Type) } | L2: coa:send task in Asynq network_commands queue | M2: go test -race -tags=integration ./internal/fup/ -run TestFUPScanner | N2: Idempotency key prevents duplicate CoA enqueue | 80% warning fires separately from 100% breach | O2: Redis SCAN is non-deterministic — use SCAN 0 MATCH 'usage:*' COUNT 1000 | P2: Done | Q2: feat(fup): FUP-001 FUP scanner with 80% warning and 100% CoA trigger
A3: FUP-002 | B3: Week 9 | C3: CoA send task with exponential backoff | D3: FR-FUP-002 | E3: DDS §5.3 | F3: FUP-001 | G3: Qwen3-14B-Q4_K_M | H3: ~5,000 | I3: You are a Go 1.21 backend engineer. Project: ISP BSS/OSS. Stack: Go 1.21, PostgreSQL 15, Redis 7.2 Sentinel, Asynq. Rules: no global state | all errors wrapped with fmt.Errorf | all DB calls use context.Context | decimal.Decimal for ALL money | never log plaintext PII (aadhaar/pan/mobile) | structured JSON logs via zerolog. Package naming: internal/{module}, pkg/{shared}. FR being implemented: [PASTE ONE FR LINE FROM SRS §2.1] DDS reference: [PASTE RELEVANT SCAFFOLD FROM DDS] | J3: System block + FR-FUP-002 + DDS §5.3 SendReliableCoA code. Generate internal/tasks/coa_task.go with HandleCoASendTask(ctx, task) error. Dial NAS UDP :1700. Set 3s deadline. Send CoA packet. Read response. If response.Code != CodeCoAACK: return fmt.Errorf wrapped error (triggers Asynq retry). Max 5 retries via asynq.MaxRetry(5). | K3: func TestCoATask_RetriesOnNAK(t *testing.T) { // mock NAS UDP server returning CoA-NAK task := buildCoATask("10.0.0.1", sess1Packet) err := HandleCoASendTask(ctx, task) assert.Error(t, err) // must return error to trigger Asynq retry } | L3: Error returned on NAK so Asynq retries | M3: go test -race ./internal/tasks/ -run TestCoATask | N3: coaAckTotal metric incremented | Timeout (deadline exceeded) also returns error | Nil return only on CodeCoAACK | O3: Model may swallow error on NAK and return nil — Asynq won't retry | P3: Done | Q3: feat(tasks): FUP-002 CoA send task with reliable delivery
A4: FUP-003 | B4: Week 9 | C4: Dead-letter monitor + PagerDuty alert | D4: FR-FUP-003 | E4: DDS §5.3 dead-letter monitor | F4: FUP-002 | G4: Qwen3-14B-Q4_K_M | H4: ~4,000 | I4: You are a Go 1.21 backend engineer. Project: ISP BSS/OSS. Stack: Go 1.21, PostgreSQL 15, Redis 7.2 Sentinel, Asynq. Rules: no global state | all errors wrapped with fmt.Errorf | all DB calls use context.Context | decimal.Decimal for ALL money | never log plaintext PII (aadhaar/pan/mobile) | structured JSON logs via zerolog. Package naming: internal/{module}, pkg/{shared}. FR being implemented: [PASTE ONE FR LINE FROM SRS §2.1] DDS reference: [PASTE RELEVANT SCAFFOLD FROM DDS] | J4: System block + FR-FUP-003 + DDS §5.3 Monitor code. Generate internal/tasks/deadletter_monitor.go with Monitor.Run(ctx). Poll every 30s: inspector.GetQueueInfo('network_commands'). If info.Dead > 0: call alerter.Trigger('dead_letter_queue_non_empty'). Set deadLetterQueueDepth gauge metric. | K4: func TestDeadLetterMonitor_AlertsOnNonZero(t *testing.T) { // inject task into dead-letter queue mockAlerter := &MockAlerter{} monitor := NewMonitor(inspector, mockAlerter) monitor.runOnce(ctx) assert.True(t, mockAlerter.WasTriggered("dead_letter_queue_non_empty")) } | L4: Alerter triggered when dead-letter depth > 0 | M4: go test -race ./internal/tasks/ -run TestDeadLetterMonitor | N4: Alert fires within 30s of task hitting dead-letter | Metric set to 0 when queue empty | O4: Model may use time.Sleep instead of ticker — must use ticker for testability | P4: Done | Q4: feat(tasks): FUP-003 dead-letter monitor with 30s polling

Sheet 🔑 API + Auth
A1: Session ID | B1: Phase/Week | C1: Task Title | D1: FR IDs | E1: Doc Reference | F1: Prerequisites | G1: Model | H1: Est. Context Tokens | I1: System Block (paste first) | J1: LM Studio Prompt (paste verbatim) | K1: Test You Write First (before LM Studio) | L1: Expected Output | M1: Verification Command | N1: Quality Gates | O1: Risk Flags | P1: Status | Q1: Commit Message | R1: Notes
A2: API-001 | B2: Week 10 | C2: JWT middleware + role extraction | D2: FR-SEC-005 | E2: DDS §5.7 | F2: ENV-006 | G2: Qwen3-14B-Q4_K_M | H2: ~4,500 | I2: You are a Go 1.21 backend engineer. Project: ISP BSS/OSS. Stack: Go 1.21, PostgreSQL 15, Redis 7.2 Sentinel, Asynq. Rules: no global state | all errors wrapped with fmt.Errorf | all DB calls use context.Context | decimal.Decimal for ALL money | never log plaintext PII (aadhaar/pan/mobile) | structured JSON logs via zerolog. Package naming: internal/{module}, pkg/{shared}. FR being implemented: [PASTE ONE FR LINE FROM SRS §2.1] DDS reference: [PASTE RELEVANT SCAFFOLD FROM DDS] | J2: System block + FR-SEC-005 + DDS §5.7 JWTMiddleware + RequireRole code. Generate internal/middleware/auth.go. JWTMiddleware: parse Bearer token, validate signature, store role in context. RequireRole(roles ...string): check role from context, return 403 if not in allowed list. Emit structured audit log on every state-modifying call. | K2: func TestRequireRole_WrongRoleReturns403(t *testing.T) { token := mintToken("csr") // CSR role req := httptest.NewRequest("PATCH", "/api/v1/wallets/recharge", nil) req.Header.Set("Authorization", "Bearer "+token) rec := httptest.NewRecorder() handler := RequireRole("billing_admin")(http.HandlerFunc(func(w http.ResponseWriter, r *http.Request) {w.WriteHeader(200)})) handler.ServeHTTP(rec, req) assert.Equal(t, 403, rec.Code) } | L2: 403 returned for wrong role | M2: go test -race ./internal/middleware/ -run TestRequireRole | N2: Expired token returns 401 | Missing token returns 401 | Correct role returns 200 | O2: Model may use JWT Claims as map[string]interface{} instead of typed struct — use typed Claims struct | P2: Done | Q2: feat(middleware): API-001 JWT middleware with role-based access control
A3: API-002 | B3: Week 10 | C3: Subscriber health endpoint — single-call diagnostic | D3: FR-OBS-004 | E3: DDS §5.9, API §7 | F3: API-001, AAA-002 | G3: Qwen3-14B-Q4_K_M | H3: ~5,500 | I3: You are a Go 1.21 backend engineer. Project: ISP BSS/OSS. Stack: Go 1.21, PostgreSQL 15, Redis 7.2 Sentinel, Asynq. Rules: no global state | all errors wrapped with fmt.Errorf | all DB calls use context.Context | decimal.Decimal for ALL money | never log plaintext PII (aadhaar/pan/mobile) | structured JSON logs via zerolog. Package naming: internal/{module}, pkg/{shared}. FR being implemented: [PASTE ONE FR LINE FROM SRS §2.1] DDS reference: [PASTE RELEVANT SCAFFOLD FROM DDS] | J3: System block + FR-OBS-004 + DDS §5.9 GetSubscriberHealth code. Generate internal/health/subscriber.go with Handler.GetSubscriberHealth(w,r). Fan out concurrently: Redis HGETALL session:{id} AND db.GetSubscriberWithMeta(ctx, id). Assemble SubscriberHealth response with: status, wallet_balance, plan_expiry, active_session (from Redis), fup_status, last_coa_result, open_tickets, last_notification (from notification_log). Must complete in ≤200ms (NFR-PERF-002). | K3: func TestSubscriberHealth_SingleCallAssembly(t *testing.T) { seedActiveSession(t, 1) // Redis seedSubscriber(t, 1) // DB req := authRequest("GET", "/api/v1/subscribers/1/health", "noc_engineer") rec := httptest.NewRecorder() handler.GetSubscriberHealth(rec, req) assert.Equal(t, 200, rec.Code) var resp SubscriberHealth json.Unmarshal(rec.Body.Bytes(), &resp) assert.NotNil(t, resp.ActiveSession) assert.Equal(t, "active", resp.Status) } | L3: 200 with assembled SubscriberHealth JSON | M3: go test -race -tags=integration ./internal/health/ && go test -bench=BenchmarkSubscriberHealth # p99 < 200ms | N3: sync.WaitGroup used for concurrent fan-out | active_session nil when no Redis key | Response under 200ms | O3: Model may do sequential DB calls instead of concurrent — must use goroutines + WaitGroup | P3: Done | Q3: feat(health): API-002 subscriber health endpoint with concurrent fan-out
A4: API-003 | B4: Week 10 | C4: Core API routes — subscribers CRUD | D4: FR-AAA-004, FR-SEC-002 | E4: API §7 /api/v1/subscribers | F4: API-001, CRY-002 | G4: Qwen3-14B-Q4_K_M | H4: ~5,000 | I4: You are a Go 1.21 backend engineer. Project: ISP BSS/OSS. Stack: Go 1.21, PostgreSQL 15, Redis 7.2 Sentinel, Asynq. Rules: no global state | all errors wrapped with fmt.Errorf | all DB calls use context.Context | decimal.Decimal for ALL money | never log plaintext PII (aadhaar/pan/mobile) | structured JSON logs via zerolog. Package naming: internal/{module}, pkg/{shared}. FR being implemented: [PASTE ONE FR LINE FROM SRS §2.1] DDS reference: [PASTE RELEVANT SCAFFOLD FROM DDS] | J4: System block + API §7 subscriber endpoints. Generate internal/api/subscribers.go with: POST /api/v1/subscribers: validate CAF+mobile (E.164), encrypt Aadhaar+PAN via AESEncryptor before DB insert, return 201. GET /api/v1/subscribers/{id}: return profile (never return decrypted PII). PATCH /api/v1/subscribers/{id}: update plan or status. | K4: func TestCreateSubscriber_EncryptsPII(t *testing.T) { body := `{"caf_number":"CAF-001","username":"test1","mobile_number":"+919876543210","plan_id":1,"aadhaar":"123456789012","registered_state":"TN"}` req := authRequest("POST", "/api/v1/subscribers", "billing_admin", body) rec := httptest.NewRecorder() handler.ServeHTTP(rec, req) assert.Equal(t, 201, rec.Code) // verify plaintext NOT in DB row := db.QueryRow("SELECT aadhaar_encrypted FROM kyc_verifications WHERE subscriber_id=$1", 1) var enc string row.Scan(&enc) assert.NotEqual(t, "123456789012", enc) assert.True(t, strings.HasPrefix(enc, "v")) } | L4: Aadhaar stored as versioned ciphertext, not plaintext | M4: go test -race -tags=integration ./internal/api/ -run TestCreateSubscriber && grep -rn '123456789012' testdata/ # zero hits | N4: PII never in response JSON | Invalid mobile format returns 422 | Duplicate CAF returns 409 | O4: Model may log the request body — plaintext PII in logs (pre-commit hook catches this) | P4: Done | Q4: feat(api): API-003 subscriber CRUD with PII encryption at write
A5: API-004 | B5: Week 10 | C5: Remaining API routes — sessions, invoices, tickets | D5: FR-SUB-004, FR-NET-002 | E5: API §7 | F5: API-003 | G5: Qwen3-14B-Q4_K_M | H5: ~5,500 | I5: You are a Go 1.21 backend engineer. Project: ISP BSS/OSS. Stack: Go 1.21, PostgreSQL 15, Redis 7.2 Sentinel, Asynq. Rules: no global state | all errors wrapped with fmt.Errorf | all DB calls use context.Context | decimal.Decimal for ALL money | never log plaintext PII (aadhaar/pan/mobile) | structured JSON logs via zerolog. Package naming: internal/{module}, pkg/{shared}. FR being implemented: [PASTE ONE FR LINE FROM SRS §2.1] DDS reference: [PASTE RELEVANT SCAFFOLD FROM DDS] | J5: System block + API §7 sessions + invoices + tickets + LEA endpoints. Generate internal/api/routes.go wiring all routes to handlers. POST /sessions/{id}/disconnect → enqueue pod:send POST /sessions/{id}/fup-override → enqueue coa:send GET /invoices/{sub_id} → list GET /invoices/{id}/pdf → return PDF bytes POST /tickets → create PATCH /tickets/{id} → update status POST /lea/lookup → subscriber lookup + write lea_audit_log | K5: func TestLEALookup_WritesAuditLog(t *testing.T) { body := `{"public_ip":"203.0.113.1","port":12345,"timestamp":"2025-01-01T12:00:00Z"}` req := authRequest("POST", "/api/v1/lea/lookup", "noc_engineer_with_lea", body) rec := httptest.NewRecorder() handler.ServeHTTP(rec, req) count := db.QueryRow("SELECT COUNT(*) FROM lea_audit_log").Scan(&n) assert.Equal(t, 1, n) } | L5: LEA lookup creates audit log record | M5: go test -race -tags=integration ./internal/api/ -run TestLEALookup | N5: LEA audit log is written BEFORE returning response | PDF Content-Type header set correctly | O5: Model may return 200 for LEA when no subscriber found — must return 404 | P5: Done | Q5: feat(api): API-004 session, invoice, ticket, LEA routes

Sheet 📊 Revenue + Franchise
A1: Session ID | B1: Phase/Week | C1: Task Title | D1: FR IDs | E1: Doc Reference | F1: Prerequisites | G1: Model | H1: Est. Context Tokens | I1: System Block (paste first) | J1: LM Studio Prompt (paste verbatim) | K1: Test You Write First (before LM Studio) | L1: Expected Output | M1: Verification Command | N1: Quality Gates | O1: Risk Flags | P1: Status | Q1: Commit Message | R1: Notes
A2: REV-001 | B2: Week 11 | C2: Unbilled subscriber report query | D2: FR-REV-001, NFR-BIZ-001 | E2: MDS §4.8, DDS §5.10 | F2: DB-013, DB-003 | G2: Qwen3-14B-Q4_K_M | H2: ~4,000 | I2: You are a Go 1.21 backend engineer. Project: ISP BSS/OSS. Stack: Go 1.21, PostgreSQL 15, Redis 7.2 Sentinel, Asynq. Rules: no global state | all errors wrapped with fmt.Errorf | all DB calls use context.Context | decimal.Decimal for ALL money | never log plaintext PII (aadhaar/pan/mobile) | structured JSON logs via zerolog. Package naming: internal/{module}, pkg/{shared}. FR being implemented: [PASTE ONE FR LINE FROM SRS §2.1] DDS reference: [PASTE RELEVANT SCAFFOLD FROM DDS] | J2: System block + FR-REV-001 + MDS §4.8 unbilled SQL. Generate internal/revenue/reconcile.go with GetUnbilledActiveSubscribers(ctx) ([]db.UnbilledSubscriber, error). Query from MDS §4.8: LEFT JOIN subscribers with invoices for current month WHERE invoice IS NULL AND status='active'. Must run in < 60s for 20,000 subscribers (NFR-BIZ-001) — use idx_revenue_unbilled index. | K2: func TestUnbilledReport_FindsMissingInvoices(t *testing.T) { // seed: 5 active subscribers, 3 have invoices this month unbilled, err := GetUnbilledActiveSubscribers(ctx) assert.NoError(t, err) assert.Len(t, unbilled, 2) // 2 missing invoices } | L2: Returns exactly 2 unbilled subscribers | M2: go test -race -tags=integration ./internal/revenue/ -run TestUnbilledReport | N2: EXPLAIN output uses idx_revenue_unbilled | Query runs in < 2s on test data | O2: Current month boundary — use date_trunc('month', NOW()) not hardcoded date | P2: Done | Q2: feat(revenue): REV-001 unbilled subscriber report
A3: REV-002 | B3: Week 11 | C3: Ledger reconciliation + variance alert | D3: FR-REV-002 | E3: MDS §4.8 | F3: DB-007, REV-001 | G3: Qwen3-14B-Q4_K_M | H3: ~4,000 | I3: You are a Go 1.21 backend engineer. Project: ISP BSS/OSS. Stack: Go 1.21, PostgreSQL 15, Redis 7.2 Sentinel, Asynq. Rules: no global state | all errors wrapped with fmt.Errorf | all DB calls use context.Context | decimal.Decimal for ALL money | never log plaintext PII (aadhaar/pan/mobile) | structured JSON logs via zerolog. Package naming: internal/{module}, pkg/{shared}. FR being implemented: [PASTE ONE FR LINE FROM SRS §2.1] DDS reference: [PASTE RELEVANT SCAFFOLD FROM DDS] | J3: System block + FR-REV-002 + MDS §4.8 reconciliation SQL. Generate GetLedgerVariance(ctx) (decimal.Decimal, error) function. Query: SUM(wallet_balance) vs SUM(credit entries) - SUM(debit entries). Return absolute variance. If variance > 0.01: caller should alert. | K3: func TestLedgerVariance_ZeroOnCleanData(t *testing.T) { variance, err := GetLedgerVariance(ctx) assert.NoError(t, err) assert.True(t, variance.LessThanOrEqual(decimal.NewFromFloat(0.01))) } | L3: Variance = 0.00 on clean seeded data | M3: go test -race -tags=integration ./internal/revenue/ -run TestLedgerVariance | N3: Uses decimal.Decimal not float64 | Alert triggered when variance injected artificially | O3: Float precision in SQL SUM — cast to NUMERIC in query | P3: Done | Q3: feat(revenue): REV-002 ledger reconciliation with variance detection
A4: REV-003 | B4: Week 11 | C4: 30-day collections forecast | D4: FR-REV-004 | E4: MDS §4.8 | F4: REV-001 | G4: Qwen3-14B-Q4_K_M | H4: ~4,000 | I4: You are a Go 1.21 backend engineer. Project: ISP BSS/OSS. Stack: Go 1.21, PostgreSQL 15, Redis 7.2 Sentinel, Asynq. Rules: no global state | all errors wrapped with fmt.Errorf | all DB calls use context.Context | decimal.Decimal for ALL money | never log plaintext PII (aadhaar/pan/mobile) | structured JSON logs via zerolog. Package naming: internal/{module}, pkg/{shared}. FR being implemented: [PASTE ONE FR LINE FROM SRS §2.1] DDS reference: [PASTE RELEVANT SCAFFOLD FROM DDS] | J4: System block + FR-REV-004. Generate BuildCollectionsForecast(ctx, days int) (*CollectionsForecast, error). Query subscribers with plan_expiry in next N days. Segment by: wallet_balance >= plan.price (will_renew), wallet_balance < plan.price (at_risk), plan_expiry < NOW() (lapsed). Return counts and expected revenue per segment. | K4: func TestCollectionsForecast_Segments(t *testing.T) { forecast, err := BuildCollectionsForecast(ctx, 30) assert.NoError(t, err) assert.Greater(t, forecast.WillRenewCount, 0) assert.GreaterOrEqual(t, forecast.ExpectedRevenue.InexactFloat64(), 0.0) } | L4: Forecast with at least one will_renew subscriber from seed data | M4: go test -race -tags=integration ./internal/revenue/ -run TestCollectionsForecast | N4: At-risk + lapsed segments populated correctly | Revenue uses decimal.Decimal | O4: Model may not join plans table for price — required for at-risk calculation | P4: Done | Q4: feat(revenue): REV-003 30-day collections forecast
A5: FRN-001 | B5: Week 11 | C5: Franchise row-level isolation middleware | D5: FR-FRN-001 | E5: MDS §4.10 | F5: DB-001, API-001 | G5: Qwen3-14B-Q4_K_M | H5: ~4,500 | I5: You are a Go 1.21 backend engineer. Project: ISP BSS/OSS. Stack: Go 1.21, PostgreSQL 15, Redis 7.2 Sentinel, Asynq. Rules: no global state | all errors wrapped with fmt.Errorf | all DB calls use context.Context | decimal.Decimal for ALL money | never log plaintext PII (aadhaar/pan/mobile) | structured JSON logs via zerolog. Package naming: internal/{module}, pkg/{shared}. FR being implemented: [PASTE ONE FR LINE FROM SRS §2.1] DDS reference: [PASTE RELEVANT SCAFFOLD FROM DDS] | J5: System block + FR-FRN-001 + MDS §4.10 data isolation. Generate internal/franchise/middleware.go with FranchiseScopeMiddleware. For requests with role 'lco_partner': extract franchise_id from JWT claim and store in context. In all DB query helpers: if ctx has franchise_id → append AND franchise_id = $N to WHERE clause. Test that LCO cannot read another LCO's subscribers. | K5: func TestFranchiseIsolation_BlocksCrossLCOAccess(t *testing.T) { // Franchise 1 and Franchise 2 each have 1 subscriber tokenF1 := mintLCOToken(franchiseID: 1) req := authRequest("GET", "/api/v1/subscribers", tokenF1) rec := httptest.NewRecorder() handler.ServeHTTP(rec, req) var subs []Subscriber json.Unmarshal(rec.Body.Bytes(), &subs) assert.Len(t, subs, 1) // only F1's subscriber, not F2's } | L5: LCO sees only their own subscribers | M5: go test -race -tags=integration ./internal/franchise/ -run TestFranchiseIsolation | N5: Parent ISP (no franchise_id) sees ALL subscribers | LCO cannot pass franchise_id override in query string | O5: Model may put isolation in handler, not middleware — must be middleware so it cannot be bypassed | P5: Done | Q5: feat(franchise): FRN-001 franchise row-level isolation middleware
A6: FRN-002 | B6: Week 11 | C6: LCO commission calculation on recharge | D6: FR-FRN-002 | E6: MDS §4.10 | F6: BIL-002, FRN-001 | G6: Qwen3-14B-Q4_K_M | H6: ~4,000 | I6: You are a Go 1.21 backend engineer. Project: ISP BSS/OSS. Stack: Go 1.21, PostgreSQL 15, Redis 7.2 Sentinel, Asynq. Rules: no global state | all errors wrapped with fmt.Errorf | all DB calls use context.Context | decimal.Decimal for ALL money | never log plaintext PII (aadhaar/pan/mobile) | structured JSON logs via zerolog. Package naming: internal/{module}, pkg/{shared}. FR being implemented: [PASTE ONE FR LINE FROM SRS §2.1] DDS reference: [PASTE RELEVANT SCAFFOLD FROM DDS] | J6: System block + FR-FRN-002. Generate internal/franchise/commission.go with CalculateAndRecordCommission(ctx, rechargeAmount decimal.Decimal, franchiseID int) error. Lookup commission_rate_pct from franchises table. commission = rechargeAmount * rate / 100 Insert into lco_ledger with recharge_amount and commission_amount. Must run inside same transaction as wallet recharge. | K6: func TestCommission_CorrectAmount(t *testing.T) { seedFranchise(t, id:1, rate:10.0) // 10% commission err := CalculateAndRecordCommission(ctx, decimal.NewFromFloat(799.00), 1) assert.NoError(t, err) ledger := getLCOLedger(1) assert.Equal(t, "79.90", ledger.CommissionAmount.String()) } | L6: Commission = 79.90 (10% of 799.00) | M6: go test -race -tags=integration ./internal/franchise/ -run TestCommission | N6: Uses decimal.Decimal | Runs in same transaction as recharge | Franchise not found returns error | O6: Model may use float64 — 10% of 799.00 in float = 79.89999... not 79.90 | P6: Done | Q6: feat(franchise): FRN-002 LCO commission calculation

Sheet 🌐 Portal
A1: Session ID | B1: Phase/Week | C1: Task Title | D1: FR IDs | E1: Doc Reference | F1: Prerequisites | G1: Model | H1: Est. Context Tokens | I1: System Block (paste first) | J1: LM Studio Prompt (paste verbatim) | K1: Test You Write First (before LM Studio) | L1: Expected Output | M1: Verification Command | N1: Quality Gates | O1: Risk Flags | P1: Status | Q1: Commit Message | R1: Notes
A2: POR-001 | B2: Week 12 | C2: Subscriber JWT auth + portal routes | D2: FR-SUB-001..005 | E2: MDS §4.9 | F2: API-001 | G2: Qwen3-14B-Q4_K_M | H2: ~4,500 | I2: You are a Go 1.21 backend engineer. Project: ISP BSS/OSS. Stack: Go 1.21, PostgreSQL 15, Redis 7.2 Sentinel, Asynq. Rules: no global state | all errors wrapped with fmt.Errorf | all DB calls use context.Context | decimal.Decimal for ALL money | never log plaintext PII (aadhaar/pan/mobile) | structured JSON logs via zerolog. Package naming: internal/{module}, pkg/{shared}. FR being implemented: [PASTE ONE FR LINE FROM SRS §2.1] DDS reference: [PASTE RELEVANT SCAFFOLD FROM DDS] | J2: System block + MDS §4.9 portal pages. Generate web/portal/auth.go with subscriber-scoped JWT (claims: subscriber_id only, no roles). Routes: GET /portal/login (SMS OTP form), POST /portal/login (verify OTP, issue JWT), GET /portal/dashboard, GET /portal/invoices, GET /portal/renew, POST /portal/tickets. Middleware: verify subscriber JWT, inject subscriber_id into context. | K2: func TestPortalAuth_InvalidJWTBlocked(t *testing.T) { req := httptest.NewRequest("GET", "/portal/dashboard", nil) req.Header.Set("Authorization", "Bearer invalid_token") rec := httptest.NewRecorder() portalMux.ServeHTTP(rec, req) assert.Equal(t, 401, rec.Code) } | L2: 401 on invalid token | M2: go test -race ./web/portal/ -run TestPortalAuth | N2: Subscriber JWT cannot access admin API routes | Portal JWT cannot contain role claims | O2: Model may reuse admin JWT secret — must be a separate PORTAL_JWT_SECRET env var | P2: Done | Q2: feat(portal): POR-001 subscriber-scoped JWT auth and route setup | R2: Keep Qwen3-14B — requires JWT logic / concurrent Redis+DB fan-out reasoning.
A3: POR-002 | B3: Week 12 | C3: Real-time usage dashboard page | D3: FR-SUB-001, FR-SUB-002 | E3: MDS §4.9 Dashboard page | F3: POR-001, AAA-002 | G3: Qwen3-14B-Q4_K_M | H3: ~5,000 | I3: You are a Go 1.21 backend engineer. Project: ISP BSS/OSS. Stack: Go 1.21, PostgreSQL 15, Redis 7.2 Sentinel, Asynq. Rules: no global state | all errors wrapped with fmt.Errorf | all DB calls use context.Context | decimal.Decimal for ALL money | never log plaintext PII (aadhaar/pan/mobile) | structured JSON logs via zerolog. Package naming: internal/{module}, pkg/{shared}. FR being implemented: [PASTE ONE FR LINE FROM SRS §2.1] DDS reference: [PASTE RELEVANT SCAFFOLD FROM DDS] | J3: System block + FR-SUB-001 + MDS §4.9. Generate web/portal/dashboard.go with DashboardHandler(w,r). Fetch: subscriber plan+wallet from DB AND real-time usage from Redis HGETALL usage:{session_id}. Render HTML template with: current speed profile, GB used / GB total as progress bar, days until expiry, wallet balance, link to renew. Polls /portal/api/usage every 60s via JavaScript. | K3: func TestDashboard_ShowsUsage(t *testing.T) { seedSession(t, 1, gbUsed: 1500) req := portalRequest("GET", "/portal/dashboard", subscriberID:1) rec := httptest.NewRecorder() handler.ServeHTTP(rec, req) assert.Contains(t, rec.Body.String(), "1500") assert.Contains(t, rec.Body.String(), "3300") } | L3: HTML contains GB used and GB total | M3: go test ./web/portal/ -run TestDashboard && go vet ./web/portal/ | N3: Redis read for real-time data | Graceful fallback if no active session (show last known) | O3: Model may read usage from PostgreSQL (slow) — must read from Redis for real-time | P3: Done | Q3: feat(portal): POR-002 real-time usage dashboard | R3: Keep Qwen3-14B — requires JWT logic / concurrent Redis+DB fan-out reasoning.
A4: POR-003 | B4: Week 12 | C4: One-tap renewal with Razorpay deeplink | D4: FR-SUB-003 | E4: MDS §4.9 | F4: POR-001, BIL-002 | G4: Llama3.1-8B-Q5_K_M | H4: ~4,000 | I4: You are a Go 1.21 backend engineer. Project: ISP BSS/OSS. Stack: Go 1.21, PostgreSQL 15, Redis 7.2 Sentinel, Asynq. Rules: no global state | all errors wrapped with fmt.Errorf | all DB calls use context.Context | decimal.Decimal for ALL money | never log plaintext PII (aadhaar/pan/mobile) | structured JSON logs via zerolog. Package naming: internal/{module}, pkg/{shared}. FR being implemented: [PASTE ONE FR LINE FROM SRS §2.1] DDS reference: [PASTE RELEVANT SCAFFOLD FROM DDS] | J4: System block + FR-SUB-003. Generate web/portal/renew.go with RenewHandler. GET /portal/renew: show current plan price and Razorpay payment button. POST /portal/renew/initiate: generate transaction_token = uuid.New().String(). Create Razorpay order via API. Return redirect to Razorpay checkout URL. POST /portal/renew/callback: verify Razorpay signature, call WalletService.Recharge() with transaction_token. | K4: func TestRenewal_IdempotentCallback(t *testing.T) { // simulate Razorpay callback twice with same payment_id first := postRazorpayCallback(t, paymentID:"pay_abc") second := postRazorpayCallback(t, paymentID:"pay_abc") assert.Equal(t, 200, first.Code) assert.Equal(t, 200, second.Code) // idempotent — no double credit bal := getSubscriberBalance(1) assert.Equal(t, "799.00", bal) // credited only once } | L4: Balance 799.00 after two identical callbacks | M4: go test -race -tags=integration ./web/portal/ -run TestRenewal | N4: HMAC verified on callback | transaction_token persisted before Razorpay order created | O4: Razorpay signature verification must happen on raw POST body before JSON parse | P4: Done | Q4: feat(portal): POR-003 one-tap Razorpay renewal with idempotent callback | R4: Switched to Llama3.1-8B — HTML template + payment routing is boilerplate; 8B handles it well.
A5: POR-004 | B5: Week 12 | C5: Notification history + ticket list pages | D5: FR-SUB-004, FR-SUB-005 | E5: MDS §4.9 | F5: POR-001, NOT-001 | G5: Llama3.1-8B-Q5_K_M | H5: ~4,000 | I5: You are a Go 1.21 backend engineer. Project: ISP BSS/OSS. Stack: Go 1.21, PostgreSQL 15, Redis 7.2 Sentinel, Asynq. Rules: no global state | all errors wrapped with fmt.Errorf | all DB calls use context.Context | decimal.Decimal for ALL money | never log plaintext PII (aadhaar/pan/mobile) | structured JSON logs via zerolog. Package naming: internal/{module}, pkg/{shared}. FR being implemented: [PASTE ONE FR LINE FROM SRS §2.1] DDS reference: [PASTE RELEVANT SCAFFOLD FROM DDS] | J5: System block + FR-SUB-004 + FR-SUB-005. Generate web/portal/notifications.go (GET /portal/notifications: list last 20 notification_log entries for subscriber) and web/portal/tickets.go (GET /portal/tickets: list tickets; POST /portal/tickets: create new ticket). HTML render with channel icon (WhatsApp/SMS/email), event type, timestamp, delivery status badge. | K5: func TestNotificationHistory_ShowsDeliveryStatus(t *testing.T) { seedNotifLog(t, subscriberID:1, status:"delivered") req := portalRequest("GET", "/portal/notifications", 1) rec := httptest.NewRecorder() handler.ServeHTTP(rec, req) assert.Contains(t, rec.Body.String(), "delivered") } | L5: HTML contains 'delivered' status for seeded log | M5: go test ./web/portal/ -run TestNotificationHistory && go test ./web/portal/ -run TestTickets | N5: Subscriber can only see their own notification_log entries | Ticket creation returns ticket ID | O5: Model may expose other subscriber's logs — ensure WHERE subscriber_id = {jwt.subscriber_id} | P5: Done | Q5: feat(portal): POR-004 notification history and ticket management pages | R5: Switched to Llama3.1-8B — HTML template + payment routing is boilerplate; 8B handles it well.

Sheet 🧪 Integration Tests
A1: Test ID | B1: Module | C1: Scenario | D1: FR Covered | E1: Prerequisites | F1: Command to Run | G1: Expected Result | H1: Pass Criteria | I1: Status | J1: Notes
A2: INT-AAA-001 | B2: RADIUS | C2: Active subscriber gets Access-Accept | D2: FR-AAA-002 | E2: AAA-002, DB-003 seed | F2: go test -tags=integration -run TestHandleAuth_ActiveSubscriberAccepted ./internal/radius/ | G2: radius.CodeAccessAccept returned | H2: Code = AccessAccept | latency metric emitted | I2: Done
A3: INT-AAA-002 | B3: RADIUS | C3: Invalid password returns Access-Reject | D3: FR-AAA-002 | E3: AAA-002 | F3: go test -tags=integration -run TestHandleAuth_InvalidPassword ./internal/radius/ | G3: radius.CodeAccessReject returned | H3: Code = AccessReject | I3: Done
A4: INT-AAA-003 | B4: RADIUS | C4: Suspended subscriber gets Access-Reject | D4: FR-AAA-002 | E4: AAA-002, DB-003 seed | F4: go test -tags=integration -run TestHandleAuth_SuspendedSubscriber ./internal/radius/ | G4: radius.CodeAccessReject | H4: Code = AccessReject | session not cached | I4: Done
A5: INT-AAA-004 | B5: RADIUS | C5: 11 failures triggers 15-min ban | D5: FR-SEC-001 | E5: AAA-004 | F5: go test -tags=integration -run TestBruteForce_BlocksAt10Failures ./internal/radius/ | G5: 11th attempt rejected | H5: Ban key in Redis with 15min TTL | I5: Done
A6: INT-AAA-005 | B6: RADIUS | C6: Duplicate Interim-Update not double-counted | D6: FR-AAA-003 | E6: AAA-003 | F6: go test -tags=integration -run TestDedup_DuplicateInterimSkipped -count=3 ./internal/radius/ | G6: Counter incremented once only | H6: Redis counter = single increment value | dedup metric +1 | I6: Done
A7: INT-BIL-001 | B7: Billing | C7: Wallet recharge creates ledger entries | D7: FR-BIL-003 | E7: BIL-002 | F7: go test -tags=integration -run TestWalletRecharge_DoubleLedger ./internal/billing/ | G7: debit + credit entries in wallet_ledgers | balance updated | H7: wallet_ledgers has 2 rows | subscribers.wallet_balance updated | I7: Done
A8: INT-BIL-002 | B8: Billing | C8: Duplicate transaction_token returns same TX | D8: FR-BIL-005 | E8: BIL-002 | F8: go test -tags=integration -run TestWalletRecharge_Idempotent ./internal/billing/ | G8: Second call returns same TX ID | balance unchanged | H8: tx1.ID == tx2.ID | balance = single recharge amount | I8: Done
A9: INT-BIL-003 | B9: Billing | C9: Razorpay webhook with valid HMAC accepted | D9: FR-SEC-004 | E9: BIL-003 | F9: go test -tags=integration -run TestWebhookHMAC_ValidSignatureAccepted ./internal/billing/ | G9: 200 OK | wallet credited | H9: Status 200 | ledger credit entry created | I9: Done
A10: INT-BIL-004 | B10: Billing | C10: Razorpay webhook with invalid HMAC rejected | D10: FR-SEC-004 | E10: BIL-003 | F10: go test -tags=integration -run TestWebhookHMAC_InvalidSignatureRejected ./internal/billing/ | G10: 400 Bad Request | wallet unchanged | H10: Status 400 | no ledger entry | metric webhookHMACFailures +1 | I10: Done
A11: INT-BIL-005 | B11: Billing | C11: GST invoice TN intrastate | D11: FR-BIL-001 | E11: BIL-001 | F11: go test -run TestCalculateGstInvoice_TN ./internal/billing/ | G11: CGST=71.91 SGST=71.91 IGST=0 Total=942.82 | H11: Exact decimal values match | no float64 in code (grep check) | I11: Done
A12: INT-BIL-006 | B12: Billing | C12: GST constraint blocks dual tax | D12: FR-BIL-001 | E12: DB-006 | F12: psql -c "INSERT INTO invoices(...,cgst_amount,igst_amount) VALUES(...,71.91,143.82);" | G12: DB raises constraint violation | H12: psql returns ERROR 23514 | no row inserted | I12: Done | J12: scripts/int_bil_006_gst_constraint.sh - schema-level, needs real PostgreSQL
A13: INT-FUP-001 | B13: FUP | C13: 100% usage breach enqueues CoA task | D13: FR-FUP-001 | E13: FUP-001 | F13: go test -tags=integration -run TestFUPScanner_EnqueuesCoAOn100Pct ./internal/fup/ | G13: coa:send task in Asynq queue | H13: Asynq network_commands queue has 1 task of type coa:send | I13: Done
A14: INT-FUP-002 | B14: FUP | C14: 80% usage breach enqueues warning notification | D14: FR-FUP-004 | E14: FUP-001 | F14: go test -tags=integration -run TestFUPScanner_Warns80Pct ./internal/fup/ | G14: notif:fup_warning task in Asynq queue | H14: Asynq notifications queue has 1 task | idempotency key prevents duplicate | I14: Done
A15: INT-FUP-003 | B15: FUP | C15: CoA NAK triggers Asynq retry | D15: FR-FUP-002 | E15: FUP-002 | F15: go test -tags=integration -run TestCoATask_RetriesOnNAK ./internal/tasks/ | G15: Error returned → Asynq retries | H15: asynq.Task.Retried == 1 after mock NAK | coaAckTotal label nak +1 | I15: Done | J15: Implemented in ./internal/fup/ (handler lives there, not ./internal/tasks/)
A16: INT-FUP-004 | B16: FUP | C16: 5 CoA failures → dead-letter + alert | D16: FR-FUP-003 | E16: FUP-002, FUP-003 | F16: go test -tags=integration -run TestDeadLetterMonitor_AlertsOnNonZero ./internal/tasks/ | G16: Alert triggered within 30s | H16: mockAlerter.WasTriggered('dead_letter_queue_non_empty') == true | I16: Done | J16: Implemented in ./internal/fup/ (handler lives there, not ./internal/tasks/)
A17: INT-NOTIF-001 | B17: Notifications | C17: DND subscriber: marketing suppressed | D17: FR-NOTIF-008 | E17: NOT-001 | F17: go test -tags=integration -run TestDispatcher_DND_SuppressesMarketing ./internal/notifications/ | G17: No WhatsApp sent | notification_log status='suppressed_dnd' | H17: No Meta API call made | DB log row created with suppressed_dnd | I17: Done
A18: INT-NOTIF-002 | B18: Notifications | C18: WhatsApp send logs provider_message_id | D18: FR-NOTIF-009 | E18: NOT-002 | F18: go test -tags=integration -run TestWhatsApp_SendTemplate_LogsProviderID ./internal/notifications/ | G18: notification_log.provider_message_id = 'wamid.xxx' | H18: DB row with non-empty provider_message_id | channel='whatsapp' | I18: Done
A19: INT-NOTIF-003 | B19: Notifications | C19: Meta delivery callback updates status | D19: FR-NOTIF-011 | E19: NOT-003 | F19: go test -tags=integration -run TestWhatsAppWebhook_UpdatesDeliveryStatus ./internal/notifications/ | G19: notification_log.delivery_status='delivered' | H19: DB row updated from 'sent' to 'delivered' | I19: Done
A20: INT-NOTIF-004 | B20: Notifications | C20: Invalid Meta webhook HMAC rejected | D20: FR-NOTIF-011 | E20: NOT-003 | F20: go test -tags=integration -run TestWhatsAppWebhook_InvalidHMAC ./internal/notifications/ | G20: 400 returned | DB unchanged | H20: Status 400 | no DB update | I20: Done
A21: INT-SEC-001 | B21: Security | C21: Admin API with no JWT returns 401 | D21: FR-SEC-005 | E21: API-001 | F21: go test -tags=integration -run TestRequireRole_NoToken ./internal/middleware/ | G21: 401 Unauthorized | H21: Status 401 | no data returned | I21: Done
A22: INT-SEC-002 | B22: Security | C22: CSR cannot access billing_admin routes | D22: FR-SEC-005 | E22: API-001 | F22: go test -tags=integration -run TestRequireRole_WrongRoleReturns403 ./internal/middleware/ | G22: 403 Forbidden | H22: Status 403 | I22: Done
A23: INT-SEC-003 | B23: Security | C23: PII stored encrypted, not plaintext | D23: FR-SEC-002 | E23: API-003, CRY-002 | F23: go test -tags=integration -run TestCreateSubscriber_EncryptsPII ./internal/api/ | G23: aadhaar_encrypted starts with 'v' | H23: Column value has version prefix | grep for '123456789012' in DB = zero rows | I23: Done
A24: INT-SEC-004 | B24: Security | C24: Cross-rotation: v1 ciphertext decryptable after v2 rotation | D24: FR-SEC-003 | E24: CRY-003, CRY-004 | F24: go test -run TestDecrypt_CrossKeyVersion ./pkg/crypto/ | G24: Plaintext restored correctly | H24: Exact match to original plaintext | no error | I24: Done
A25: INT-NOTIF-005 | B25: Notifications | C25: FUP warning task dispatches TMPL-001 | D25: FR-FUP-004 | E25: NOT-005 | F25: go test -tags=integration -run TestFUPWarningTask_DispatchesWhatsApp ./internal/tasks/ | G25: WhatsApp sent with TMPL-001 | H25: notification_log.template_id = 'TMPL-001' | channel='whatsapp' | I25: Done | J25: Implemented in ./internal/fup/ (handler lives there, not ./internal/tasks/)
A26: INT-REV-001 | B26: Revenue | C26: Unbilled subscriber report finds missing invoices | D26: FR-REV-001 | E26: REV-001, DB seeded | F26: go test -tags=integration -run TestUnbilledReport ./internal/revenue/ | G26: Returns 2 unbilled subscribers | H26: Count matches seeded deficit | query uses index | I26: Done
A27: INT-REV-002 | B27: Revenue | C27: Ledger variance = 0 on clean data | D27: FR-REV-002 | E27: REV-002 | F27: go test -tags=integration -run TestLedgerVariance ./internal/revenue/ | G27: variance <= 0.01 | H27: Decimal comparison passes | I27: Done
A28: INT-REV-003 | B28: Revenue | C28: Collections forecast segments correctly | D28: FR-REV-004 | E28: REV-003 | F28: go test -tags=integration -run TestCollectionsForecast ./internal/revenue/ | G28: at least 1 will_renew, 1 at_risk | H28: Both segments populated | revenue uses decimal | I28: Done
A29: INT-SUB-001 | B29: Portal | C29: Subscriber portal shows real-time usage | D29: FR-SUB-001 | E29: POR-002, AAA-002 | F29: go test -tags=integration -run TestDashboard_ShowsUsage ./web/portal/ | G29: HTML contains GB used and total | H29: Response body contains seeded usage values | I29: Done | J29: Implemented in ./internal/portal/ (handlers live there, not ./web/portal/)
A30: INT-SUB-002 | B30: Portal | C30: Renewal callback is idempotent | D30: FR-SUB-003 | E30: POR-003 | F30: go test -tags=integration -run TestRenewal_IdempotentCallback ./web/portal/ | G30: Same balance after 2 identical callbacks | H30: Balance = single plan price | tx1.ID == tx2.ID | I30: Done | J30: Implemented in ./internal/portal/; renewal callback added (POR-003 gap)
A31: INT-SUB-003 | B31: Portal | C31: Notification history scoped to subscriber | D31: FR-SUB-005 | E31: POR-004 | F31: go test -tags=integration -run TestNotificationHistory_ScopedToSubscriber ./web/portal/ | G31: Only own notification_log rows returned | H31: Row count = seeded rows for that subscriber only | I31: Done | J31: Implemented in ./internal/portal/ (handlers live there, not ./web/portal/)
A32: INT-FRN-001 | B32: Franchise | C32: LCO sees only own subscribers | D32: FR-FRN-001 | E32: FRN-001 | F32: go test -tags=integration -run TestFranchiseIsolation_BlocksCrossLCOAccess ./internal/franchise/ | G32: LCO F1 sees 1 subscriber not 2 | H32: Response list length = 1 | no F2 subscriber data | I32: Done | J32: Implemented in ./internal/revenue/ (franchise code lives there)
A33: INT-FRN-002 | B33: Franchise | C33: LCO commission calculated on recharge | D33: FR-FRN-002 | E33: FRN-002 | F33: go test -tags=integration -run TestCommission_CorrectAmount ./internal/franchise/ | G33: commission = 79.90 on 799.00 recharge at 10% | H33: lco_ledger row with correct decimal amount | I33: Done | J33: Implemented in ./internal/revenue/ (franchise code lives there)
A34: INT-PII-001 | B34: Security | C34: Pre-commit hook blocks PII in logs | D34: NFR-SEC-002 | E34: ENV-008 | F34: echo 'log.Info().Str("aadhaar",raw).Msg("test")' > /tmp/test_pii.go && .git/hooks/pre-commit | G34: Exit code 1 (PII leak detected) | H34: Script exits 1 | message printed | I34: Done | J34: scripts/int_pii_001_precommit_hook.sh - hook was a no-op (grep -P failed silently); fixed
A35: INT-HEALTH-001 | B35: API | C35: Subscriber health returns assembled view | D35: FR-OBS-004 | E35: API-002 | F35: go test -tags=integration -run TestSubscriberHealth_SingleCallAssembly ./internal/health/ | G35: 200 with active_session not nil | H35: active_session populated from Redis | status from DB | response < 200ms | I35: Done

Sheet ⚡ NFR Load Tests
A1: Test ID | B1: NFR | C1: Category | D1: Prerequisite Sessions | E1: Setup Command | F1: Test Command | G1: Pass Threshold | H1: Actual Result | I1: Status | J1: Notes
A2: NFR-PERF-001 | B2: NFR-PERF-001 | C2: Latency | D2: AAA-001..005 complete | E2: # Pre-seed 5,000 active sessions python3 scripts/seed_radius_sessions.py --count 5000 # Start AAA daemon go run cmd/radiusd/main.go & | F2: radperf --server localhost:1812 --secret my_shared_secret --rate 5000 --duration 600 --users scripts/test_users.txt | G2: p99 ≤ 15ms | error rate < 0.01% | H2: PASS. p99 10.4ms at 5,000 req/s (budget 15ms); p50 4.538ms, p95 7.934ms. 149,850 requests, 0 errors, 0 dropped to saturation. Measured with production bcrypt cost 12. | I2: Done | J2: RESOLVED 2026-08-10 by the fast-verifier cache, the first of the two options this note proposed. internal/radius/verifiercache.go caches HMAC-SHA256(secret, password || passwordHash) in Redis after the first successful bcrypt, so repeat auths skip cost-12 entirely. DDS 5.1 cost 12 is retained, so there is no spec deviation and the conflict is dissolved rather than traded away. Daemon-side counters at 5,000 req/s: 249,850 cache hits vs 39,960 misses; server-side mean auth 3.211ms. The verifier is bound to the current password hash, so a password change self-invalidates it immediately. Separately, the harness never set RADIUS_VERIFIER_SECRET, so radiusd exited at config validation and reported a 100 percent error rate that read as a latency failure; fixed in commit cb1d2bf. Rerun: ./scripts/run_nfr_tests.sh
A3: NFR-PERF-002 | B3: NFR-PERF-002 | C3: Latency | D3: API-001..004 complete | E3: # Start API service go run cmd/api/main.go & | F3: k6 run --vus 500 --duration 5m scripts/k6_api_load.js | G3: p99 ≤ 200ms | error rate < 0.1% | H3: PASS. p99 43.7-74.1ms at 500 VUs (budget 200ms). 0.00% errors over 260,952 checks. | I3: Done | J3: k6 via grafana/k6 container against the wired API. Measured at 20,000 seeded subscribers. Rerun: ./scripts/run_nfr_tests.sh
A4: NFR-PERF-003 | B4: NFR-PERF-003 | C4: Latency | D4: NOT-001..005 complete | E4: # Verify WhatsApp test credentials set in .env | F4: go test -tags=integration -run TestFUPWarningTask_E2ELatency -timeout 30s ./internal/tasks/ | G4: Notification dispatched in ≤ 5s from task enqueue | I4: Todo | J4: Not run: needs live Meta WhatsApp credentials and a Meta test number. The dispatch path itself is covered by INT-NOTIF-005 and INT-NOTIF-002 against a stub Meta endpoint.
A5: NFR-SCAL-001 | B5: NFR-SCAL-001 | C5: Concurrency | D5: AAA-001..005, all DB migrations | E5: # Pre-seed 20,000 subscribers python3 scripts/seed_radius_sessions.py --count 20000 go run cmd/radiusd/main.go & | F5: # Ramp phase radperf --rate 67 --duration 300 --users scripts/20k_users.txt # Hold phase radperf --rate 333 --duration 3600 --users scripts/20k_users.txt | G5: p99 ≤ 15ms during hold | no OOM | radius_worker_queue_depth < 50 | I5: Blocked | J5: Not run: the 1-hour hold is impractical here, and it inherits the NFR-PERF-001 bcrypt conflict. Resolve that first. The harness exists: ./scripts/run_nfr_tests.sh with RATE/DURATION, plus scripts/seed_load for 20k subscribers.
A6: NFR-AVAIL-001 | B6: NFR-AVAIL-001 | C6: Availability | D6: ENV-007 stack running | E6: docker compose up -d | F6: # Chaos: kill Redis primary docker compose stop redis_primary sleep 5 redis-cli -p 26379 -h localhost sentinel master bss_master | G6: New master elected within 3s | RADIUS auth resumes within 5s | I6: Todo | J6: Not run: needs the full docker-compose Sentinel stack (3 sentinels + 2 replicas) rather than the single Redis the test harness starts.
A7: NFR-DUR-001 | B7: NFR-DUR-001 | C7: Durability | D7: AAA-001..005 running | E7: # Start continuous accounting storm go run scripts/accounting_storm.go & | F7: # Kill Redis replica mid-storm docker compose stop redis_replica_1 sleep 10 docker compose start redis_replica_1 # Check accounting stream completeness | G7: Zero accounting records lost | Redis AOF shows all entries | I7: Todo | J7: Not run: the accounting_storm.go the row references does not exist. cmd/radload could be extended to generate the accounting storm.
A8: NFR-BIZ-001 | B8: NFR-BIZ-001 | C8: Revenue | D8: REV-001 complete, 20k subscribers seeded | E8: # Seed 20,000 active subscribers with varied invoice history python3 scripts/seed_billing_data.py --subscribers 20000 | F8: time psql -h localhost -U postgres -d isp_bss_oss -c " SELECT COUNT(*) FROM subscribers s LEFT JOIN invoices i ON i.subscriber_id=s.id AND date_trunc('month',i.created_at)=date_trunc('month',NOW()) WHERE s.status='active' AND i.id IS NULL;" | G8: Query completes in ≤ 60s | H8: PASS. Unbilled query 14.5-15.0ms at 20,000 subscribers (budget 60,000ms). | I8: Done | J8: EXPLAIN ANALYZE run first as the row requires. Planner chooses a sequential scan at this row count, which is correct and still ~4000x inside budget; idx_revenue_unbilled exists for larger volumes. Rerun: ./scripts/run_nfr_tests.sh
A9: NFR-SEC-001 | B9: NFR-SEC-001 | C9: Security | D9: API service running with TLS | E9: # Obtain TLS cert (use mkcert for local) mkcert localhost 127.0.0.1 | F9: testssl.sh --protocols --headers --cipher-suites https://localhost:8443 | G9: TLS 1.3 only | TLS 1.2 disabled | HSTS header present | I9: Blocked | J9: Not run: the API serves plain HTTP. TLS termination is not implemented in cmd/api, so there is no TLS 1.3 endpoint to scan. Needs a TLS listener or a documented terminating proxy first.
A10: NFR-SEC-002 | B10: NFR-SEC-002 | C10: Security | D10: All modules complete | E10: # Run full codebase PII scan | F10: grep -rni 'aadhaar\|\.pan\b\|mobile_number' --include='*.go' . | grep -v '_test.go\|encrypt\|db\.' | grep 'log\.\|Print' | G10: Zero hits | H10: PASS. Zero hits across the codebase and zero PII field names in runtime service logs. | I10: Done | J10: Two checks: the row's grep across all Go source, plus a scan of the running API container logs. Also enforced pre-commit by .githooks/pre-commit and verified by scripts/int_pii_001_precommit_hook.sh.

Sheet 📎 Prompt Snippets
A1: Snippet Name | B1: Content — copy and paste into LM Studio
A2: SYSTEM BLOCK — paste at start of EVERY session | B2: You are a Go 1.21 backend engineer. Project: ISP BSS/OSS. Stack: Go 1.21, PostgreSQL 15, Redis 7.2 Sentinel, Asynq. Rules: no global state | all errors wrapped with fmt.Errorf | all DB calls use context.Context | decimal.Decimal for ALL money | never log plaintext PII (aadhaar/pan/mobile) | structured JSON logs via zerolog. Package naming: internal/{module}, pkg/{shared}. FR being implemented: [PASTE ONE FR LINE FROM SRS §2.1] DDS reference: [PASTE RELEVANT SCAFFOLD FROM DDS]
A3: REDIS PATTERNS — paste when model hallucinates redis API | B3: # SetNX (correct go-redis v9): result, err := rdb.SetNX(ctx, key, "1", 30*time.Second).Result() # HINCRBY: err = rdb.HIncrBy(ctx, "usage:"+sessionID, "input_bytes", int64(inputOctets)).Err() # HGETALL: fields, err := rdb.HGetAll(ctx, "subscriber:"+username).Result() # Sentinel connection: rdb := redis.NewFailoverClient(&redis.FailoverOptions{ MasterName: os.Getenv("REDIS_MASTER_NAME"), SentinelAddrs: strings.Split(os.Getenv("REDIS_SENTINEL_ADDRS"), ","), })
A4: PGX TRANSACTION PATTERN — paste when model uses database/sql | B4: tx, err := pool.BeginTx(ctx, pgx.TxOptions{IsoLevel: pgx.Serializable}) if err != nil { return err } defer tx.Rollback(ctx) // ... do work ... return tx.Commit(ctx)
A5: ASYNQ PATTERNS — paste when model invents Asynq API | B5: # Enqueue: task := asynq.NewTask("coa:send", payload) _, err = client.Enqueue(task, asynq.Queue("network_commands"), asynq.MaxRetry(5), asynq.TaskID("coa:"+sessionID+":"+epochMinute), // idempotency ) # Handler registration: mux := asynq.NewServeMux() mux.HandleFunc("coa:send", HandleCoASendTask) # Inspector: inspector := asynq.NewInspector(asynq.RedisClientOpt{Addr: redisAddr}) info, _ := inspector.GetQueueInfo("network_commands") fmt.Println(info.Dead)
A6: DECIMAL.DECIMAL PATTERNS — paste when model uses float64 | B6: import "github.com/shopspring/decimal" # From float: base := decimal.NewFromFloat(799.00) # Arithmetic: cgst := base.Mul(decimal.NewFromFloat(9)).Div(decimal.NewFromInt(100)).Round(2) # Comparison: if variance.GreaterThan(decimal.NewFromFloat(0.01)) { alert() } # To string: fmt.Println(total.String()) // "942.82"
A7: ZEROLOG PATTERN — paste when model uses fmt.Printf or log.Printf | B7: import "github.com/rs/zerolog" logger := zerolog.New(os.Stdout).With().Timestamp().Str("service","billing").Logger() // With correlation ID: ctxLogger := logger.With().Str("correlation_id", correlationID).Logger() ctxLogger.Info().Str("event","wallet_recharge").Int("subscriber_id", subID).Msg("recharge completed") // NEVER DO: logger.Info().Str("aadhaar", rawAadhaar).Msg("test") // PII leak
A8: JWT PATTERN — paste when model uses outdated JWT libraries | B8: import jwt "github.com/golang-jwt/jwt/v5" type Claims struct { SubscriberID int `json:"sub_id,omitempty"` Role string `json:"role,omitempty"` jwt.RegisteredClaims } # Sign: token := jwt.NewWithClaims(jwt.SigningMethodHS256, claims) ss, _ := token.SignedString([]byte(secret)) # Parse: tok, err := jwt.ParseWithClaims(tokenStr, &Claims{}, func(t *jwt.Token) (interface{}, error) { return []byte(secret), nil })
A9: META WHATSAPP API PATTERN — paste when model invents Meta API | B9: POST https://graph.facebook.com/v17.0/{phone_number_id}/messages Authorization: Bearer {access_token} Content-Type: application/json { "messaging_product": "whatsapp", "to": "+919876543210", "type": "template", "template": { "name": "fup_warning", "language": {"code": "en"}, "components": [ { "type": "body", "parameters": [ {"type": "text", "text": "Rajan"}, {"type": "text", "text": "2640"}, {"type": "text", "text": "3300"} ] } ] } }
A10: LAYEH RADIUS PATTERN — paste when model invents radius API | B10: import "layeh.com/radius" import "layeh.com/radius/rfc2865" # Get username from packet: username := rfc2865.UserName_GetString(r.Packet) # Build Access-Accept: response := r.Response(radius.CodeAccessAccept) rfc2865.ReplyMessage_SetString(response, "Welcome") w.Write(response) # Build Access-Reject: response := r.Response(radius.CodeAccessReject) w.Write(response)
A11: GOOSE MIGRATION TEMPLATE | B11: +goose Up CREATE TABLE example ( id SERIAL PRIMARY KEY, name VARCHAR(100) NOT NULL, created_at TIMESTAMPTZ NOT NULL DEFAULT NOW() ); CREATE INDEX idx_example_name ON example(name); +goose Down DROP TABLE IF EXISTS example CASCADE;
A12: SESSION RESET CHECKLIST — run when model fails twice in a row | B12: 1. Close the LM Studio chat (do NOT continue in same context) 2. Open a NEW chat 3. Paste SYSTEM BLOCK again from scratch 4. Paste ONLY the failing test (not previous outputs) 5. Rephrase the request more specifically 6. Add one constraint that was missing: e.g. 'Use SetNX not Get+Set for atomicity' 7. If fails again on 3rd attempt → ask Claude (this chat) to debug the logic first
... A15: MODEL SELECTION GUIDE — which model to load for each session type | B15: WHEN TO LOAD Qwen3-14B-Q4_K_M (~9.1 GB VRAM at 4k ctx): - pkg/crypto (AES encryption, key versioning logic) - internal/radius (RADIUS protocol, auth hot path logic) - internal/billing (GST decimal math, dunning state machine) - internal/fup (FUP threshold logic, CoA retry) - internal/notifications (WhatsApp API, DND logic) - internal/middleware (JWT validation, RBAC) - internal/health (concurrent fan-out, subscriber health assembly) - DB-010, DB-011 (partitioned tables — complex pg_partman SQL) - POR-001, POR-002 (JWT auth logic, Redis real-time usage) Rule: use when the task requires multi-step reasoning or protocol accuracy. WHEN TO LOAD Llama3.1-8B-Q5_K_M (~5.1 GB VRAM at 4k ctx, 6.5 GB at 8k ctx): - DB-001..DB-009, DB-012..DB-015 (standard SQL CREATE TABLE migrations) - POR-003 (Razorpay HTML form + callback handler — standard HTTP code) - POR-004 (HTML list pages — notification history, ticket CRUD) - internal/revenue (SQL queries you've already written in MDS §4.8) - internal/franchise (boilerplate row-filter middleware) - Any session generating HTML templates or standard CRUD handlers Rule: use when the output is mostly boilerplate with predictable structure. HOW TO SWITCH MODELS in LM Studio: 1. Click current model name in top bar → "Eject Model" (frees VRAM) 2. Wait for VRAM to clear (check nvidia-smi: usage drops to ~0.3 GB) 3. Search and load the target model 4. Set context limit (4096 for Qwen3, up to 8192 for Llama3.1-8B) Switching takes ~30 seconds. Plan your session order to minimise switches. CHECK VRAM BEFORE EVERY SESSION: nvidia-smi --query-gpu=memory.used,memory.free --format=csv,noheader # Qwen3 session: used ~9100 MB, free ~2900 MB ✓ # Llama session: used ~5100 MB, free ~6900 MB ✓ # If free < 1500 MB → eject model and reload fresh
